Workbook

Sheet Empresas Generadoras
B2: EMPRESAS GENERADORAS PARTICIPANTES DEL MERCADO DE CORTO PLAZO
B4: RAZÓN SOCIAL | C4: RUT | D4: SEGMENTO | E4: GIRO
B5: AASA Energía S.A. | C5: 76.596.827-5 | D5: PMGD, Generador | E5: Generación de Energía Eléctrica
B6: Abastible S.A. | C6: 91.806.000-6 | D6: PMGD | E6: GENERACION DE ENERGIA ELECTRICA EN OTRAS CENTRALES N.C.P.
B7: Acciona Energía Chile Holdings S.A. | C7: 76.437.712-5 | D7: Generador, PMGD | E7: Generación de Energía Eléctrica
B8: Acierta Energía SpA | C8: 77.333.033-6 | D8: PMGD | E8: Generación de Energía
B9: Aela Generación S.A. | C9: 76.489.426-K | D9: Transmisor Dedicado, Generador | E9: Generación de Energía Eléctrica
B10: AES Andes S.A. | C10: 94.272.000-9 | D10: Transmisor Dedicado, Generador, Transmisor Zonal | E10: Generación, Transmisión y Venta de Energía Eléctrica
B11: Aggreko Chile Limitada | C11: 76.625.330-K | D11: PMGD | E11: Generación de energía eléctrica en otras centrales N.C.P.
B12: Agrícola Ancalí Limitada | C12: 79.757.460-0 | D12: PMGD | E12: Agrícola, Lechería, Ganadería, Harás y Generación Eléctrica
B13: Agrosolar IV SpA | C13: 76.363.219-9 | D13: PMGD | E13: Generación en Otras Centrales N.C.P.
B14: Agrosolar V SpA | C14: 76.363.218-0 | D14: PMGD | E14: Generación en Otras Centrales N.C.P.
B15: Aguas Andinas S.A. | C15: 61.808.000-5 | D15: PMGD | E15: Servicios Sanitarios
... B695: Xue Solar SpA | C695: 76.466.222-9 | D695: PMGD | E695: Generación de Energía Eléctrica

Sheet Pagos Laterales
B2: Pagos Laterales Unitarios en Balances de Trasferencias de Energía en $/kWh de los últimos doce meses
B13: MES | C13: Retiros [MWh] | D13: Precio Estabilizado [mill. CLP] | E13: Sobrecosto Energía [mill. CLP] | F13: Sobrecosto P-D [mill. CLP] | G13: Reserva Hídrica [mill. CLP] | H13: SSCC [mill. CLP] | I13: TOTAL [mill. CLP] | J13: Precio Estabilizado Unitario [CLP/kWh] | K13: Sobrecosto Energía Unitario [CLP/kWh] | L13: Sobrecosto P-D Unitario [CLP/kWh] | M13: Reserva Hídrica Unitario [CLP/kWh] | N13: SSCC Unitario [CLP/kWh] | O13: TOTAL Unitario [CLP/kWh]
B14: 45658 | C14: 6907522.1 | D14: 34506.959 | E14: 21819.233 | F14: 839.62882 | G14: 0 | H14: 18219.523 | I14: =+SUM(D14:H14) -> 75385.344 | J14: =+D14*1000/$C14 -> 4.9955626 | K14: =+E14*1000/$C14 -> 3.1587641 | L14: =+F14*1000/$C14 -> 0.12155282 | M14: =+G14*1000/$C14 -> 0 | N14: =+H14*1000/$C14 -> 2.6376351 | O14: =+I14*1000/$C14 -> 10.913515
B15: 45689 | C15: 6216776.1 | D15: 23516.962 | E15: 21899.529 | F15: 1214.0559 | G15: 0 | H15: 15041.63 | I15: =+SUM(D15:H15) -> 61672.176 | J15: =+D15*1000/$C15 -> 3.7828227 | K15: =+E15*1000/$C15 -> 3.5226504 | L15: =+F15*1000/$C15 -> 0.19528706 | M15: =+G15*1000/$C15 -> 0 | N15: =+H15*1000/$C15 -> 2.4195225 | O15: =+I15*1000/$C15 -> 9.9202827
B16: 45717 | C16: 6817653.4 | D16: 19880.165 | E16: 22366.772 | F16: 849.96286 | G16: 0 | H16: 16573.524 | I16: =+SUM(D16:H16) -> 59670.424 | J16: =+D16*1000/$C16 -> 2.9159836 | K16: =+E16*1000/$C16 -> 3.2807142 | L16: =+F16*1000/$C16 -> 0.12467088 | M16: =+G16*1000/$C16 -> 0 | N16: =+H16*1000/$C16 -> 2.4309719 | O16: =+I16*1000/$C16 -> 8.7523405
B17: 45748 | C17: 6355658.8 | D17: 6389.6396 | E17: 17361.669 | F17: 742.26272 | G17: 0 | H17: 23342.1 | I17: =+SUM(D17:H17) -> 47835.672 | J17: =+D17*1000/$C17 -> 1.0053465 | K17: =+E17*1000/$C17 -> 2.7316868 | L17: =+F17*1000/$C17 -> 0.11678769 | M17: =+G17*1000/$C17 -> 0 | N17: =+H17*1000/$C17 -> 3.6726483 | O17: =+I17*1000/$C17 -> 7.5264694
B18: 45778 | C18: 6726678.7 | D18: 8363.1054 | E18: 12883.015 | F18: 547.60978 | G18: 0 | H18: 17373.384 | I18: =+SUM(D18:H18) -> 39167.114 | J18: =+D18*1000/$C18 -> 1.2432741 | K18: =+E18*1000/$C18 -> 1.9152119 | L18: =+F18*1000/$C18 -> 0.081408643 | M18: =+G18*1000/$C18 -> 0 | N18: =+H18*1000/$C18 -> 2.5827581 | O18: =+I18*1000/$C18 -> 5.8226528
B19: 45809 | C19: 6785598.5 | D19: -1682.1095 | E19: 16049.377 | F19: 420.23437 | G19: 0 | H19: 22875.225 | I19: =+SUM(D19:H19) -> 37662.727 | J19: =+D19*1000/$C19 -> -0.24789405 | K19: =+E19*1000/$C19 -> 2.3652117 | L19: =+F19*1000/$C19 -> 0.061930332 | M19: =+G19*1000/$C19 -> 0 | N19: =+H19*1000/$C19 -> 3.3711433 | O19: =+I19*1000/$C19 -> 5.5503913
B20: 45839 | C20: 6879473.8 | D20: 3422.1827 | E20: 15523.369 | F20: 834.07116 | G20: 0 | H20: 26642.669 | I20: =+SUM(D20:H20) -> 46422.292 | J20: =+D20*1000/$C20 -> 0.49744833 | K20: =+E20*1000/$C20 -> 2.2564762 | L20: =+F20*1000/$C20 -> 0.12124055 | M20: =+G20*1000/$C20 -> 0 | N20: =+H20*1000/$C20 -> 3.8727773 | O20: =+I20*1000/$C20 -> 6.7479423
B21: 45870 | C21: 6623523.9 | D21: 16466.25 | E21: 24744.639 | F21: 385.36841 | G21: 0 | H21: 22934.263 | I21: =+SUM(D21:H21) -> 64530.52 | J21: =+D21*1000/$C21 -> 2.4860256 | K21: =+E21*1000/$C21 -> 3.7358722 | L21: =+F21*1000/$C21 -> 0.05818178 | M21: =+G21*1000/$C21 -> 0 | N21: =+H21*1000/$C21 -> 3.462547 | O21: =+I21*1000/$C21 -> 9.7426266
B22: 45901 | C22: 6235722.2 | D22: 27057.87 | E22: 20684.308 | F22: 433.41587 | G22: 0 | H22: 21436.899 | I22: =+SUM(D22:H22) -> 69612.494 | J22: =+D22*1000/$C22 -> 4.3391718 | K22: =+E22*1000/$C22 -> 3.317067 | L22: =+F22*1000/$C22 -> 0.069505319 | M22: =+G22*1000/$C22 -> 0 | N22: =+H22*1000/$C22 -> 3.4377572 | O22: =+I22*1000/$C22 -> 11.163501
B23: 45931 | C23: 6501494 | D23: 35110.133 | E23: 20115.932 | F23: 468.9478 | G23: 0 | H23: 15817.907 | I23: =+SUM(D23:H23) -> 71512.92 | J23: =+D23*1000/$C23 -> 5.4003177 | K23: =+E23*1000/$C23 -> 3.0940476 | L23: =+F23*1000/$C23 -> 0.072129237 | M23: =+G23*1000/$C23 -> 0 | N23: =+H23*1000/$C23 -> 2.4329649 | O23: =+I23*1000/$C23 -> 10.99946
B24: 45962 | C24: 6476488.1 | D24: 37354.829 | E24: 22517.655 | F24: 547.81268 | G24: 0 | H24: 16172.505 | I24: =+SUM(D24:H24) -> 76592.801 | J24: =+D24*1000/$C24 -> 5.7677599 | K24: =+E24*1000/$C24 -> 3.4768311 | L24: =+F24*1000/$C24 -> 0.084584835 | M24: =+G24*1000/$C24 -> 0 | N24: =+H24*1000/$C24 -> 2.4971103 | O24: =+I24*1000/$C24 -> 11.826286
B25: 45992 | C25: 6992495.6 | D25: 38712.885 | E25: 23932.25 | F25: 699.81096 | G25: 0 | H25: 12942.711 | I25: =+SUM(D25:H25) -> 76287.656 | J25: =+D25*1000/$C25 -> 5.5363473 | K25: =+E25*1000/$C25 -> 3.4225621 | L25: =+F25*1000/$C25 -> 0.10008029 | M25: =+G25*1000/$C25 -> 0 | N25: =+H25*1000/$C25 -> 1.850943 | O25: =+I25*1000/$C25 -> 10.909933

Sheet Clientes Libres
B2: =+"Consumo de Clientes Libres en Balance de Transferencias de Energía (valores en MWh) en últimos 12 meses" -> Consumo de Clientes Libres en Balance de Transferencias de Energía (valores en MWh) en últimos 12 meses
B4: BARRA | C4: RUT CLIENTE | D4: NOMBRE O RAZÓN SOCIAL DEL CLIENTE | E4: SUMINISTRADOR | F4: CONECTADO A LA RED DE | G4: ene-25 | H4: feb-25 | I4: mar-25 | J4: abr-25 | K4: may-25 | L4: jun-25 | M4: jul-25 | N4: ago-25 | O4: sept-25 | P4: oct-25 | Q4: nov-25 | R4: dic-25
A5: BULEVAR RENTAS INMOBILIARIAS S.A. | B5: A.BLANCAS_____013 | C5: 76231235-2 | D5: BULEVAR RENTAS INMOBILIARIAS S.A. | E5: ENGIE | F5: COMPAÑÍA GENERAL DE ELECTRICIDAD S.A. | G5: 238.47221 | H5: 213.51893 | I5: 227.27544 | J5: 199.33756 | K5: 206.73139 | L5: 240.72241 | M5: 233.14583 | N5: 209.21579 | O5: 192.86457 | P5: 206.48778 | Q5: 204.07863 | R5: 245.27048
A6: ITI CHILE S A | B6: A.BLANCAS_____013 | C6: 76343170-3 | D6: ITI CHILE S A | E6: ABASTIBLE | F6: COMPAÑÍA GENERAL DE ELECTRICIDAD S.A. | G6: 173.4834 | H6: 175.9434 | I6: 193.455 | J6: 195.2526 | K6: 188.1414 | L6: 174.1236 | M6: 185.8158 | N6: 0
A7: CM MADERERA SPA | B7: A.BLANCAS_____013 | C7: 76682070-0 | D7: CM MADERERA SPA | E7: EMOAC | F7: COMPAÑÍA GENERAL DE ELECTRICIDAD S.A. | G7: 147.12208 | H7: 142.59564 | I7: 163.6506 | J7: 147.15251 | K7: 108.76004 | L7: 105.92224 | M7: 116.99053 | N7: 126.27187 | O7: 115.78594 | P7: 144.85153 | Q7: 141.77569 | R7: 151.92806
A8: SOLVAY PEROXIDOS DE LOS ANDES IND Y COM LTDA | B8: A.BLANCAS_____013 | C8: 76819130-1 | D8: SOLVAY PEROXIDOS DE LOS ANDES IND Y COM LTDA | E8: ENEL_GENERACION | F8: COMPAÑÍA GENERAL DE ELECTRICIDAD S.A. | G8: 1654.1887 | H8: 1303.5872 | I8: 1633.03 | J8: 1667.2958 | K8: 1607.6389 | L8: 1660.1453 | M8: 1704.6069 | N8: 1526.4678 | O8: 1392.8629 | P8: 1458.8173 | Q8: 1406.5455 | R8: 1448.0355
A9: ESSBIO S.A. | B9: A.BLANCAS_____013 | C9: 76833300-9 | D9: ESSBIO S.A. | E9: ENEL_GENERACION | F9: COMPAÑÍA GENERAL DE ELECTRICIDAD S.A. | G9: 278.01645 | H9: 245.4699 | I9: 264.83166 | J9: 245.45944 | K9: 241.41797 | L9: 233.17703 | M9: 240.06797 | N9: 253.32042 | O9: 211.7004 | P9: 230.23691 | Q9: 262.89375 | R9: 285.26211
A10: SODIMAC S.A. | B10: A.BLANCAS_____013 | C10: 96792430-K | D10: SODIMAC S.A. | E10: ENEL_GENERACION | F10: COMPAÑÍA GENERAL DE ELECTRICIDAD S.A. | G10: 108.06722 | H10: 88.491426 | I10: 115.45741 | J10: 138.25113 | K10: 154.60582 | L10: 148.35358 | M10: 155.35289 | N10: 141.60303 | O10: 118.4197 | P10: 118.32599 | Q10: 104.88056 | R10: 110.26093
A11: ORIZON S A | B11: A.BLANCAS_____013 | C11: 96929960-7 | D11: ORIZON S A | E11: EMOAC | F11: COMPAÑÍA GENERAL DE ELECTRICIDAD S.A. | G11: 1430.2599 | H11: 1472.1928 | I11: 1901.2739 | J11: 1367.2073 | K11: 1047.58 | L11: 892.03119 | M11: 722.89537 | N11: 721.35021 | O11: 154.85532 | P11: 434.90106 | Q11: 907.00144 | R11: 1672.2454
A12: AGUAS SAN PEDRO S A | B12: A.BLANCAS_____013 | C12: 99593190-7 | D12: AGUAS SAN PEDRO S A | E12: ENERGY_ASSET | F12: COMPAÑÍA GENERAL DE ELECTRICIDAD S.A. | G12: 189.74092 | H12: 171.63915 | I12: 187.0821 | J12: 170.3208 | K12: 180.64658 | L12: 164.3451 | M12: 179.22383 | N12: 0
A13: GENDARMERIA DE CHILE DIRECCION REGIONAL | B13: A.HOSPICIO____013 | C13: 61004002-0 | D13: GENDARMERIA DE CHILE DIRECCION REGIONAL | E13: ENEL_GENERACION | F13: COMPAÑÍA GENERAL DE ELECTRICIDAD S.A. | G13: 195.25408 | H13: 184.05912 | I13: 199.82928 | J13: 189.72716 | K13: 201.59468 | L13: 200.1664 | M13: 212.0104 | N13: 207.86696 | O13: 199.34656 | P13: 201.7078 | Q13: 191.32512 | R13: 192.20936
A14: ZONA FRANCA DE IQUIQUE S A | B14: A.HOSPICIO____013 | C14: 70285500-4 | D14: ZONA FRANCA DE IQUIQUE S A | E14: ABASTIBLE | F14: COMPAÑÍA GENERAL DE ELECTRICIDAD S.A. | K14: 127.8571 | L14: 120.32888 | M14: 122.57651 | N14: 122.72537 | O14: 122.64399 | P14: 123.70974 | Q14: 118.96119 | R14: 124.1444
A15: ZONA FRANCA DE IQUIQUE S A | B15: A.HOSPICIO____013 | C15: 70285500-4 | D15: ZONA FRANCA DE IQUIQUE S A | E15: ATRIA_ENERGIA | F15: COMPAÑÍA GENERAL DE ELECTRICIDAD S.A. | G15: 142.34479 | H15: 126.21105 | I15: 137.55346 | J15: 126.42857
A16: SR INMOBILIARIA S.A. | B16: A.HOSPICIO____013 | C16: 76002124-5 | D16: SR INMOBILIARIA S.A. | E16: EMOAC | F16: COMPAÑÍA GENERAL DE ELECTRICIDAD S.A. | G16: 101.2306 | H16: 99.469335 | I16: 112.38493 | J16: 91.697026 | K16: 82.054595 | L16: 74.084465 | M16: 75.861695 | N16: 75.94678 | O16: 72.55472 | P16: 82.01606 | Q16: 81.794125 | R16: 91.130375
A17: BRUENING INDUSTRIAL S.A. | B17: A.HOSPICIO____013 | C17: 76035258-6 | D17: BRUENING INDUSTRIAL S.A. | E17: ACIERTA_ENERGIA | F17: COMPAÑÍA GENERAL DE ELECTRICIDAD S.A. | G17: 122.63371 | H17: 101.29145 | I17: 145.93004 | J17: 104.63326
A18: BRUENING INDUSTRIAL S.A. | B18: A.HOSPICIO____013 | C18: 76035258-6 | D18: BRUENING INDUSTRIAL S.A. | E18: GR Power Chile SpA | F18: COMPAÑÍA GENERAL DE ELECTRICIDAD S.A. | K18: 103.0184 | L18: 97.854804 | M18: 111.29014 | N18: 102.62572 | O18: 121.68428 | P18: 136.11187 | Q18: 105.24307 | R18: 102.89931
A19: AGUAS DEL ALTIPLANO S.A. | B19: A.HOSPICIO____013 | C19: 76215634-2 | D19: AGUAS DEL ALTIPLANO S.A. | E19: ACCIONA_ENERGIA | F19: COMPAÑÍA GENERAL DE ELECTRICIDAD S.A. | I19: 30.44244 | J19: 30.1322 | K19: 31.15476 | L19: 26.73076 | M19: 29.29332 | N19: 30.21312 | O19: 28.9618 | P19: 33.45692 | Q19: 29.5456 | R19: 29.07436
A20: SOC COMERCIAL RECMETAL COMPANIA LIMITADA | B20: A.HOSPICIO____013 | C20: 77612130-4 | D20: SOC COMERCIAL RECMETAL COMPANIA LIMITADA | E20: ABASTIBLE | F20: COMPAÑÍA GENERAL DE ELECTRICIDAD S.A. | G20: 11.4331 | H20: 7.48573 | I20: 8.48519 | J20: 13.89234 | K20: 16.14291 | L20: 16.98067 | M20: 19.97674 | N20: 18.81222 | O20: 16.38224 | P20: 25.06672 | Q20: 21.45773 | R20: 8.88594
A21: POWER MAS SPA | B21: A.HOSPICIO____013 | C21: 78066213-1 | D21: POWER MAS SPA | E21: ABASTIBLE | F21: COMPAÑÍA GENERAL DE ELECTRICIDAD S.A. | R21: 55.123034
A22: CENCOSUD RETAIL S.A. | B22: A.HOSPICIO____013 | C22: 81201000-K | D22: CENCOSUD RETAIL S.A. | E22: AES_GENER | F22: COMPAÑÍA GENERAL DE ELECTRICIDAD S.A. | G22: 48.66288 | H22: 51.28956 | I22: 50.51018 | J22: 40.60126 | K22: 35.5222 | L22: 32.5052 | M22: 34.13578 | N22: 32.41518 | O22: 32.81754 | P22: 39.72542 | Q22: 42.5936 | R22: 45.297
A23: FINNING CHILE SA | B23: A.HOSPICIO____013 | C23: 91489000-4 | D23: FINNING CHILE SA | E23: ENEL_GENERACION | F23: COMPAÑÍA GENERAL DE ELECTRICIDAD S.A. | G23: 22.78486 | H23: 23.36054 | I23: 22.30648 | J23: 17.68704 | K23: 18.7992 | L23: 17.4426 | M23: 23.00032 | N23: 25.62434 | O23: 29.9544 | P23: 29.16158 | Q23: 26.24426 | R23: 27.1145
A24: KOMATSU CHILE S.A. | B24: A.HOSPICIO____013 | C24: 96843130-7 | D24: KOMATSU CHILE S.A. | E24: Innergex Energía Renovable SpA | F24: COMPAÑÍA GENERAL DE ELECTRICIDAD S.A. | G24: 38.65287 | H24: 34.435535 | I24: 38.339164 | J24: 34.453252 | K24: 35.592083 | L24: 34.209591 | M24: 34.391711 | N24: 32.59739 | O24: 32.313475 | P24: 34.585007 | Q24: 35.884904 | R24: 33.080864
A25: AGUAS DEL ALTIPLANO S.A. | B25: A.HOSPICIO____110 | C25: 76215634-2 | D25: AGUAS DEL ALTIPLANO S.A. | E25: ACCIONA_ENERGIA | F25: COMPAÑÍA GENERAL DE ELECTRICIDAD S.A. | G25: 31.4384 | H25: 25.56484
A26: POWER MAS SPA | B26: A.HOSPICIO____110 | C26: 78066213-1 | D26: POWER MAS SPA | E26: ABASTIBLE | F26: COMPAÑÍA GENERAL DE ELECTRICIDAD S.A. | Q26: 0 | R26: 0
A27: EMPRESA DE LOS FERROCARRILES DEL ESTADO | B27: A.JAHUEL______066 | C27: 61216000-7 | D27: EMPRESA DE LOS FERROCARRILES DEL ESTADO | E27: ENEL_GENERACION | F27: Cliente AT | G27: 302.8323 | H27: 0 | I27: 393.70193 | J27: 370.45034 | K27: 443.19874 | L27: 417.58704 | M27: 388.10595 | N27: 402.61309 | O27: 376.72742 | P27: 431.09221 | Q27: 335.98023 | R27: 451.14393
A28: COMUNIDAD EDIFICIO NERUDA | B28: A_DE_CORDOVA__013 | C28: 53300319-2 | D28: COMUNIDAD EDIFICIO NERUDA | E28: ACIERTA_ENERGIA | F28: ENEL DISTRIBUCIÓN CHILE S.A. | G28: 231.46715 | H28: 204.89369 | I28: 206.03389 | J28: 189.38444 | K28: 182.96742 | L28: 195.01145 | M28: 199.06715 | N28: 189.23665 | O28: 182.7261 | P28: 197.39483 | Q28: 189.42251 | R28: 200.59355
A29: EDIFICIO ALSACIA | B29: A_DE_CORDOVA__013 | C29: 53300841-0 | D29: EDIFICIO ALSACIA | E29: ENEL_GENERACION | F29: ENEL DISTRIBUCIÓN CHILE S.A. | G29: 183.1529 | H29: 157.4912 | I29: 174.2816 | J29: 161.7609 | K29: 170.4595 | L29: 181.784 | M29: 181.5629 | N29: 176.1545 | O29: 162.7237 | P29: 174.0353 | Q29: 171.1129 | R29: 191.7155
A30: EDIFICIO ISIDORA GOYENECHEA 3520 | B30: A_DE_CORDOVA__013 | C30: 53301881-5 | D30: EDIFICIO ISIDORA GOYENECHEA 3520 | E30: IMELSA_ENERGIA | F30: ENEL DISTRIBUCIÓN CHILE S.A. | G30: 144.5192 | H30: 130.8874 | I30: 130.6174 | J30: 112.2513 | K30: 99.0645 | L30: 94.8601 | M30: 109.3176 | N30: 104.4233 | O30: 111.9178 | P30: 120.6797 | Q30: 116.4133 | R30: 140.317
A31: COMUNIDAD EDIFICIO MISTRAL 615 | B31: A_DE_CORDOVA__013 | C31: 53303284-2 | D31: COMUNIDAD EDIFICIO MISTRAL 615 | E31: EMOAC | F31: ENEL DISTRIBUCIÓN CHILE S.A. | O31: 157.31414 | P31: 183.06472 | Q31: 176.47933 | R31: 188.84337
A32: COMUNIDAD EDIFICIO MISTRAL 615 | B32: A_DE_CORDOVA__013 | C32: 53303284-2 | D32: COMUNIDAD EDIFICIO MISTRAL 615 | E32: ENEL_GENERACION | F32: ENEL DISTRIBUCIÓN CHILE S.A. | G32: 221.37481 | H32: 192.46991 | I32: 207.3247 | J32: 171.36478 | K32: 171.20083 | L32: 189.09439 | M32: 185.39596 | N32: 165.7855
A33: COMUNIDAD EDIFICIO PARQUE ARAUCANO | B33: A_DE_CORDOVA__013 | C33: 53305293-2 | D33: COMUNIDAD EDIFICIO PARQUE ARAUCANO | E33: ENEL_GENERACION | F33: ENEL DISTRIBUCIÓN CHILE S.A. | G33: 313.14985 | H33: 273.82389 | I33: 297.69389 | J33: 260.79292 | K33: 246.71413 | L33: 243.77791 | M33: 266.24145 | N33: 244.4328 | O33: 231.91202 | P33: 266.33809 | Q33: 261.37481 | R33: 276.49638
A34: EDIFICIO BURGOS | B34: A_DE_CORDOVA__013 | C34: 53306785-9 | D34: EDIFICIO BURGOS | E34: IMELSA_ENERGIA | F34: ENEL DISTRIBUCIÓN CHILE S.A. | G34: 410.90246 | H34: 362.26158 | I34: 378.55075 | J34: 342.8039 | K34: 335.03773 | L34: 352.59286 | M34: 356.69693 | N34: 337.44519 | O34: 319.93454 | P34: 346.63802 | Q34: 311.05139 | R34: 346.38765
A35: COMUNIDAD EDIFICIO MATTA 530 | B35: A_DE_CORDOVA__013 | C35: 53307190-2 | D35: COMUNIDAD EDIFICIO MATTA 530 | E35: IMELSA_ENERGIA | F35: ENEL DISTRIBUCIÓN CHILE S.A. | G35: 309.1704 | H35: 268.63945 | I35: 286.34371 | J35: 256.79862 | K35: 244.6416 | L35: 251.97214 | M35: 259.22255 | N35: 259.826 | O35: 230.99026 | P35: 256.51205 | Q35: 260.01294 | R35: 289.29874
A36: EDIFICIO ISIDORA MAGDALENA | B36: A_DE_CORDOVA__013 | C36: 53307401-4 | D36: EDIFICIO ISIDORA MAGDALENA | E36: IMELSA_ENERGIA | F36: ENEL DISTRIBUCIÓN CHILE S.A. | G36: 287.522 | H36: 247.666 | I36: 268.862 | J36: 227.867 | K36: 231.815 | L36: 243.617 | M36: 247.254 | N36: 232.879 | O36: 220.558 | P36: 242.145 | Q36: 247.185 | R36: 267.903
A37: COMUNIDAD EDIFICIO APOQUINDO 3910 | B37: A_DE_CORDOVA__013 | C37: 53308832-5 | D37: COMUNIDAD EDIFICIO APOQUINDO 3910 | E37: ENEL_GENERACION | F37: ENEL DISTRIBUCIÓN CHILE S.A. | G37: 69.151 | H37: 60.877 | I37: 60.839 | J37: 47.162 | K37: 47.614 | L37: 57.362 | M37: 56.388 | N37: 49.782 | O37: 47.367 | P37: 53.116 | Q37: 55.832 | R37: 63.197
A38: EDIFICIO GOLF 82 | B38: A_DE_CORDOVA__013 | C38: 53313019-4 | D38: EDIFICIO GOLF 82 | E38: IMELSA_ENERGIA | F38: ENEL DISTRIBUCIÓN CHILE S.A. | G38: 71.627 | H38: 58.443 | I38: 62.017 | J38: 48.878 | K38: 51.581 | L38: 64.938 | M38: 67.389 | N38: 60.589 | O38: 54.475 | P38: 60.522 | Q38: 57.462 | R38: 63.644
A39: EDIFICIO MAGDALENA NORTE | B39: A_DE_CORDOVA__013 | C39: 53313325-8 | D39: EDIFICIO MAGDALENA NORTE | E39: ACIERTA_ENERGIA | F39: ENEL DISTRIBUCIÓN CHILE S.A. | G39: 124.336 | H39: 105.782 | I39: 111.261 | J39: 93.258 | K39: 98.323 | L39: 113.448 | M39: 118.066 | N39: 105.181 | O39: 97.067 | P39: 99.348 | Q39: 99.692 | R39: 114.107
A40: EDIFICIO PARQUE ANDINO | B40: A_DE_CORDOVA__013 | C40: 53313950-7 | D40: EDIFICIO PARQUE ANDINO | E40: ENEL_GENERACION | F40: ENEL DISTRIBUCIÓN CHILE S.A. | G40: 360.737 | H40: 329.751 | I40: 357.208 | J40: 290.74 | K40: 278.788 | L40: 290.574 | M40: 299.538 | N40: 285.792 | O40: 276.488 | P40: 314.779 | Q40: 304.061 | R40: 310.827
A41: COMUNIDAD EDIFICIO ARRAU | B41: A_DE_CORDOVA__013 | C41: 53315032-2 | D41: COMUNIDAD EDIFICIO ARRAU | E41: ENEL_GENERACION | F41: ENEL DISTRIBUCIÓN CHILE S.A. | G41: 348.293 | H41: 322.992 | I41: 333.113 | J41: 298.637 | K41: 271.344 | L41: 266.238 | M41: 291.714 | N41: 280.621 | O41: 277.092 | P41: 317.364 | Q41: 305.518 | R41: 338.262
A42: COMUNIDAD EDIFICIO PARQUE SUR | B42: A_DE_CORDOVA__013 | C42: 53315212-0 | D42: COMUNIDAD EDIFICIO PARQUE SUR | E42: ENEL_GENERACION | F42: ENEL DISTRIBUCIÓN CHILE S.A. | G42: 325.79362 | H42: 286.90929 | I42: 300.74592 | J42: 265.44652 | K42: 265.54037 | L42: 264.78978 | M42: 273.07198 | N42: 253.76081 | O42: 243.73316 | P42: 275.69986 | Q42: 270.21008 | R42: 295.44905
A43: COMUNIDAD EDIFICIO APOQUINDO 4700 | B43: A_DE_CORDOVA__013 | C43: 53316746-2 | D43: COMUNIDAD EDIFICIO APOQUINDO 4700 | E43: ENEL_GENERACION | F43: ENEL DISTRIBUCIÓN CHILE S.A. | R43: 81.061
A44: EDIFICIO OFICINAS DE CORDOVA | B44: A_DE_CORDOVA__013 | C44: 53317017-K | D44: EDIFICIO OFICINAS DE CORDOVA | E44: IMELSA_ENERGIA | F44: ENEL DISTRIBUCIÓN CHILE S.A. | R44: 75.583
A45: COMUNIDAD EDIFICIO ROSARIO NORTE 100 | B45: A_DE_CORDOVA__013 | C45: 53318179-1 | D45: COMUNIDAD EDIFICIO ROSARIO NORTE 100 | E45: ENEL_GENERACION | F45: ENEL DISTRIBUCIÓN CHILE S.A. | R45: 154.1931
A46: COMUNIDAD EDIFICIO NUEVA VITACURA | B46: A_DE_CORDOVA__013 | C46: 53319707-8 | D46: COMUNIDAD EDIFICIO NUEVA VITACURA | E46: ENEL_GENERACION | F46: ENEL DISTRIBUCIÓN CHILE S.A. | R46: 37.7183
A47: EDIFICIO TORRE 1 | B47: A_DE_CORDOVA__013 | C47: 53321584-K | D47: EDIFICIO TORRE 1 | E47: IMELSA_ENERGIA | F47: ENEL DISTRIBUCIÓN CHILE S.A. | G47: 311.24085 | H47: 297.33152 | I47: 299.91792 | J47: 271.43209 | K47: 272.05604 | L47: 285.18932 | M47: 300.74164 | N47: 282.90885 | O47: 272.68826 | P47: 298.01505 | Q47: 276.36527 | R47: 293.21711
A48: COMUNIDAD EDIFICIO CERRO EL PLOMO 6000 | B48: A_DE_CORDOVA__013 | C48: 53321624-2 | D48: COMUNIDAD EDIFICIO CERRO EL PLOMO 6000 | E48: ENEL_GENERACION | F48: ENEL DISTRIBUCIÓN CHILE S.A. | G48: 458.9543 | H48: 406.3467 | I48: 422.7562 | J48: 415.6484 | K48: 431.3027 | L48: 448.1462 | M48: 473.208 | N48: 444.928 | O48: 433.8013 | P48: 452.8426 | Q48: 459.3512 | R48: 480.4585
A49: CONDOMINIO TORRE CERRO EL PLOMO | B49: A_DE_CORDOVA__013 | C49: 53321991-8 | D49: CONDOMINIO TORRE CERRO EL PLOMO | E49: ENEL_GENERACION | F49: ENEL DISTRIBUCIÓN CHILE S.A. | G49: 67.37 | H49: 58.61 | I49: 64.237 | J49: 53.612 | K49: 50.208 | L49: 43.41 | M49: 45.737 | N49: 44.471 | O49: 52.414 | P49: 63.29 | Q49: 63.51 | R49: 67.877
A50: COMUNIDAD EDIFICIO TORRE APOQUINDO | B50: A_DE_CORDOVA__013 | C50: 53322520-9 | D50: COMUNIDAD EDIFICIO TORRE APOQUINDO | E50: ENEL_GENERACION | F50: ENEL DISTRIBUCIÓN CHILE S.A. | G50: 297.84607 | H50: 263.16463 | I50: 276.092 | J50: 267.37159 | K50: 277.16347 | L50: 308.40926 | M50: 331.11189 | N50: 305.01382 | O50: 287.13327 | P50: 287.02502 | Q50: 264.17001 | R50: 0
A51: COMUNIDAD EDIFICIO TORRE BADAJOZ | B51: A_DE_CORDOVA__013 | C51: 53322521-7 | D51: COMUNIDAD EDIFICIO TORRE BADAJOZ | E51: ENEL_GENERACION | F51: ENEL DISTRIBUCIÓN CHILE S.A. | G51: 214.756 | H51: 192.602 | I51: 204.922 | J51: 178.425 | K51: 168.618 | L51: 174.704 | M51: 183.828 | N51: 170.839 | O51: 163.308 | P51: 184.087 | Q51: 182.782 | R51: 0
A52: COMUNIDAD EDIFICIO MGV | B52: A_DE_CORDOVA__013 | C52: 53323749-5 | D52: COMUNIDAD EDIFICIO MGV | E52: ENEL_GENERACION | F52: ENEL DISTRIBUCIÓN CHILE S.A. | G52: 84.829 | H52: 70.954 | I52: 71.98 | J52: 58.094 | K52: 61.017 | L52: 64.39 | M52: 72.218 | N52: 66.013 | O52: 63.289 | P52: 67.615 | Q52: 63.872 | R52: 69.466
A53: CONDOMINIO EDIFICIO CENTRO KENNEDY | B53: A_DE_CORDOVA__013 | C53: 53324355-K | D53: CONDOMINIO EDIFICIO CENTRO KENNEDY | E53: AES_GENER | F53: ENEL DISTRIBUCIÓN CHILE S.A. | G53: 100.2186 | H53: 91.0973 | I53: 61.0013 | J53: 39.4885 | K53: 37.3654 | L53: 47.2986 | M53: 59.6387 | N53: 46.0935 | O53: 36.339 | P53: 45.2097 | Q53: 48.9122 | R53: 57.6634
A54: COMUNIDAD EDIFICIO OFICINAS K KENNEDY 6800 | B54: A_DE_CORDOVA__013 | C54: 53325553-1 | D54: COMUNIDAD EDIFICIO OFICINAS K KENNEDY 6800 | E54: ENEL_GENERACION | F54: ENEL DISTRIBUCIÓN CHILE S.A. | G54: 66.2486 | H54: 48.6213 | I54: 48.7678 | J54: 34.5125 | K54: 32.5355 | L54: 31.104 | M54: 29.5923 | N54: 29.7 | O54: 32.9357 | P54: 40.2049 | Q54: 37.8987 | R54: 0
A55: EDIFICIO BRITANIA | B55: A_DE_CORDOVA__013 | C55: 53331609-3 | D55: EDIFICIO BRITANIA | E55: EMOAC | F55: ENEL DISTRIBUCIÓN CHILE S.A. | H55: 206.4833 | I55: 165.28803 | J55: 194.78612 | K55: 203.74282 | L55: 231.64052 | M55: 235.5727 | N55: 214.84956 | O55: 192.15516 | P55: 193.79684 | Q55: 185.31616 | R55: 196.01812
A56: EDIFICIO LOS MILITARES | B56: A_DE_CORDOVA__013 | C56: 53332047-3 | D56: EDIFICIO LOS MILITARES | E56: IMELSA_ENERGIA | F56: ENEL DISTRIBUCIÓN CHILE S.A. | R56: 115.0846
A57: COMUNIDAD EDIFICIO KENNEDY PLAZA. | B57: A_DE_CORDOVA__013 | C57: 53332531-9 | D57: COMUNIDAD EDIFICIO KENNEDY PLAZA. | E57: ENERGY_ASSET | F57: ENEL DISTRIBUCIÓN CHILE S.A. | G57: 134.4204 | H57: 116.9474 | I57: 118.7472 | J57: 95.638 | K57: 93.6354 | L57: 103.1575 | M57: 103.0823 | N57: 102.4286 | O57: 93.8937 | P57: 104.8977 | Q57: 113.5514 | R57: 127.5671
A58: COMUNIDAD EDIFICIO TORRE LAS CONDES | B58: A_DE_CORDOVA__013 | C58: 56033550-4 | D58: COMUNIDAD EDIFICIO TORRE LAS CONDES | E58: IMELSA_ENERGIA | F58: ENEL DISTRIBUCIÓN CHILE S.A. | G58: 36.94599 | H58: 33.12918 | I58: 35.29034 | J58: 42.76341 | K58: 45.37123 | L58: 47.79166 | M58: 47.74789 | N58: 49.2035 | O58: 43.93179 | P58: 41.58637 | Q58: 37.74865 | R58: 0
A59: COMUNIDAD COMPLEJO BOULEVARD KENNEDY | B59: A_DE_CORDOVA__013 | C59: 56053060-9 | D59: COMUNIDAD COMPLEJO BOULEVARD KENNEDY | E59: ENEL_GENERACION | F59: ENEL DISTRIBUCIÓN CHILE S.A. | G59: 210.65748 | H59: 174.18915 | I59: 156.08584 | J59: 115.25419 | K59: 129.29934 | L59: 160.46845 | M59: 160.33438 | N59: 144.13115 | O59: 127.74595 | P59: 140.02042 | Q59: 143.37926 | R59: 179.47953
A60: COMUNIDAD EDIFICIO ALCANTARA 200 | B60: A_DE_CORDOVA__013 | C60: 56056910-6 | D60: COMUNIDAD EDIFICIO ALCANTARA 200 | E60: IMELSA_ENERGIA | F60: ENEL DISTRIBUCIÓN CHILE S.A. | G60: 60.3712 | H60: 52.77353 | I60: 49.63249 | J60: 45.52515 | K60: 55.42073 | L60: 73.44143 | M60: 72.4893 | N60: 67.42619 | O60: 56.34332 | P60: 45.19812 | Q60: 41.2395 | R60: 47.96297
A61: COMUNIDAD EDIFICIO TORRE CONDELL | B61: A_DE_CORDOVA__013 | C61: 56059620-0 | D61: COMUNIDAD EDIFICIO TORRE CONDELL | E61: IMELSA_ENERGIA | F61: ENEL DISTRIBUCIÓN CHILE S.A. | G61: 64.609 | H61: 55.199 | I61: 51.798 | J61: 45.888 | K61: 52.335 | L61: 84.145 | M61: 85.375 | N61: 63.738 | O61: 54.873 | P61: 46.859 | Q61: 42.305 | R61: 50.074
A62: COMUNIDAD EDIFICIO EL GOLF 99 | B62: A_DE_CORDOVA__013 | C62: 56069560-8 | D62: COMUNIDAD EDIFICIO EL GOLF 99 | E62: ENEL_GENERACION | F62: ENEL DISTRIBUCIÓN CHILE S.A. | G62: 97.3836 | H62: 84.5991 | I62: 87.5182 | J62: 60.3479 | K62: 65.4645 | L62: 92.2852 | M62: 89.8126 | N62: 82.4014 | O62: 66.0283 | P62: 62.0133 | Q62: 59.715 | R62: 66.2106
A63: COMUNIDAD EDIFICIO HUIDOBRO | B63: A_DE_CORDOVA__013 | C63: 56079880-6 | D63: COMUNIDAD EDIFICIO HUIDOBRO | E63: IMELSA_ENERGIA | F63: ENEL DISTRIBUCIÓN CHILE S.A. | G63: 165.7643 | H63: 150.0091 | I63: 167.1618 | J63: 138.5282 | K63: 136.2455 | L63: 136.0048 | M63: 131.1983 | N63: 117.5728 | O63: 115.5012 | P63: 127.9266 | Q63: 123.4235 | R63: 138.545
A64: CONDOMINIO GOLF 2001 | B64: A_DE_CORDOVA__013 | C64: 56082460-2 | D64: CONDOMINIO GOLF 2001 | E64: IMELSA_ENERGIA | F64: ENEL DISTRIBUCIÓN CHILE S.A. | G64: 314.3703 | H64: 268.4144 | I64: 291.5698 | J64: 281.5302 | K64: 287.402 | L64: 327.536 | M64: 335.9648 | N64: 305.8327 | O64: 284.6726 | P64: 290.9086 | Q64: 283.6409 | R64: 298.1276
A65: EDIFICIO APOQUINDO 3500 | B65: A_DE_CORDOVA__013 | C65: 56088630-6 | D65: EDIFICIO APOQUINDO 3500 | E65: ENEL_GENERACION | F65: ENEL DISTRIBUCIÓN CHILE S.A. | G65: 96.5379 | H65: 82.5548 | I65: 82.8266 | J65: 75.2324 | K65: 84.542 | L65: 106.8507 | M65: 107.0261 | N65: 93.7324 | O65: 83.1951 | P65: 77.0623 | Q65: 74.431 | R65: 82.7093
A66: SERVICIO SALUD OCCIDENTE HOSPITAL DR FELIX BULNES CERDA | B66: A_DE_CORDOVA__013 | C66: 61608205-1 | D66: SERVICIO SALUD OCCIDENTE HOSPITAL DR FELIX BULNES CERDA | E66: COLBUN | F66: ENEL DISTRIBUCIÓN CHILE S.A. | G66: 1704.1186 | H66: 1611.4343 | I66: 1678.4566 | J66: 1539.1036 | K66: 1623.5785 | L66: 1535.4079 | M66: 1547.9361 | N66: 1477.5969 | O66: 1363.9181 | P66: 1629.7556 | Q66: 1620.2471 | R66: 0
A67: EDIFICIO ALCANTARA APOQUINDO | B67: A_DE_CORDOVA__013 | C67: 65029896-9 | D67: EDIFICIO ALCANTARA APOQUINDO | E67: IMELSA_ENERGIA | F67: ENEL DISTRIBUCIÓN CHILE S.A. | G67: 286.12578 | H67: 254.51727 | I67: 281.45039 | J67: 253.60923 | K67: 254.20878 | L67: 289.64377 | M67: 293.99726 | N67: 268.43065 | O67: 258.65861 | P67: 276.48396 | Q67: 266.76239 | R67: 277.47549
A68: COMUNIDAD EDIFICIO DE LAS ARTES TORRE SEIS | B68: A_DE_CORDOVA__013 | C68: 65039906-4 | D68: COMUNIDAD EDIFICIO DE LAS ARTES TORRE SEIS | E68: ACIERTA_ENERGIA | F68: ENEL DISTRIBUCIÓN CHILE S.A. | G68: 310.90272 | H68: 360.834 | I68: 356.7036 | J68: 293.3165 | K68: 269.248 | L68: 269.5034 | M68: 289.6466 | N68: 274.1704 | O68: 273.291 | P68: 316.3436 | Q68: 328.7089 | R68: 346.0895
... A74: CONDOMINIO ANDES DE CORDOVA | B74: A_DE_CORDOVA__013 | C74: 65167107-8 | D74: CONDOMINIO ANDES DE CORDOVA | E74: IMELSA_ENERGIA | F74: ENEL DISTRIBUCIÓN CHILE S.A. | G74: 115.0658 | H74: 95.1114 | I74: 103.8378 | J74: 88.7426 | K74: 88.133 | L74: 100.2048 | M74: 114.267 | N74: 103.6645 | O74: 91.1469 | P74: 87.4242 | Q74: 89.3029 | R74: 101.9504
A75: EDIFICIO NUEVA CÓRDOVA | B75: A_DE_CORDOVA__013 | C75: 65205209-6 | D75: EDIFICIO NUEVA CÓRDOVA | E75: ENEL_GENERACION | F75: ENEL DISTRIBUCIÓN CHILE S.A. | G75: 131.91418 | H75: 152.25146 | I75: 160.56369
A76: EDIFICIO NUEVA CÓRDOVA | B76: A_DE_CORDOVA__013 | C76: 65205209-6 | D76: EDIFICIO NUEVA CÓRDOVA | E76: IMELSA_ENERGIA | F76: ENEL DISTRIBUCIÓN CHILE S.A. | J76: 158.87292 | K76: 178.15014 | L76: 214.91416 | M76: 220.70935 | N76: 209.23221 | O76: 179.05596 | P76: 184.78281 | Q76: 186.267 | R76: 186.04576
A77: CLUB DE GOLF SPORT FRANCES | B77: A_DE_CORDOVA__013 | C77: 70017350-K | D77: CLUB DE GOLF SPORT FRANCES | E77: EMOAC | F77: ENEL DISTRIBUCIÓN CHILE S.A. | R77: 170.6425
A78: FUNDACION CHILE | B78: A_DE_CORDOVA__013 | C78: 70300000-2 | D78: FUNDACION CHILE | E78: Cinergia Chile SpA | F78: ENEL DISTRIBUCIÓN CHILE S.A. | G78: 117.8184 | H78: 99.0688 | I78: 102.0604 | J78: 93.5205 | K78: 93.7805 | L78: 102.6945 | M78: 101.1725 | N78: 96.2179 | O78: 88.2712 | P78: 93.6141 | Q78: 94.0306 | R78: 104.4937
A79: INTEGRA SERVICIOS S.A. | B79: A_DE_CORDOVA__013 | C79: 76016027-K | D79: INTEGRA SERVICIOS S.A. | E79: ENEL_GENERACION | F79: ENEL DISTRIBUCIÓN CHILE S.A. | G79: 295.85843 | H79: 268.78624 | I79: 284.90584 | J79: 263.42544 | K79: 253.08261 | L79: 261.44209 | M79: 265.20117 | N79: 267.0264 | O79: 258.26411 | P79: 304.20194 | Q79: 291.14187 | R79: 313.04344
A80: COMERCIALIZADORA GC S.A. | B80: A_DE_CORDOVA__013 | C80: 76058347-2 | D80: COMERCIALIZADORA GC S.A. | E80: EMOAC | F80: ENEL DISTRIBUCIÓN CHILE S.A. | G80: 335.6382 | H80: 291.9179 | I80: 330.4198 | J80: 246.5996 | K80: 222.6721 | L80: 226.3151 | M80: 243.3737 | N80: 228.7694 | O80: 223.5616 | P80: 253.8112 | Q80: 259.221 | R80: 282.7615
A81: ADM DE ESTABLECIMIENTOS SOCIALES UNION EL GOLF LTDA | B81: A_DE_CORDOVA__013 | C81: 76121910-3 | D81: ADM DE ESTABLECIMIENTOS SOCIALES UNION EL GOLF LTDA | E81: NEOELECTRA_ENERGIA | F81: ENEL DISTRIBUCIÓN CHILE S.A. | G81: 122.53341 | H81: 103.5175 | I81: 107.91806 | J81: 81.95062 | K81: 71.50725 | L81: 64.30346 | M81: 88.80262 | N81: 109.60928 | O81: 97.40794 | P81: 101.67746 | Q81: 106.64235 | R81: 111.44404
A82: WHITE SPA | B82: A_DE_CORDOVA__013 | C82: 76134884-1 | D82: WHITE SPA | E82: IMELSA_ENERGIA | F82: ENEL DISTRIBUCIÓN CHILE S.A. | R82: 56.789
A83: ADMINISTRADORA DE SUPERMERCADOS HIPER LIMITADA | B83: A_DE_CORDOVA__013 | C83: 76134941-4 | D83: ADMINISTRADORA DE SUPERMERCADOS HIPER LIMITADA | E83: COLBUN | F83: ENEL DISTRIBUCIÓN CHILE S.A. | R83: 444.5977
A84: LV-PATIO RENTA INMOBILIARIA I SPA | B84: A_DE_CORDOVA__013 | C84: 76146937-1 | D84: LV-PATIO RENTA INMOBILIARIA I SPA | E84: EMOAC | F84: ENEL DISTRIBUCIÓN CHILE S.A. | G84: 202.16737 | H84: 173.64807 | I84: 173.12256 | J84: 145.68285 | K84: 153.44018 | L84: 172.12002 | M84: 167.74094 | N84: 165.29987 | O84: 152.6012 | P84: 153.83395 | Q84: 166.36015 | R84: 183.06632
A85: CONSTRUCTORA E INMOBILIARIA BERSA CERRO COLORADO S.A. | B85: A_DE_CORDOVA__013 | C85: 76154749-6 | D85: CONSTRUCTORA E INMOBILIARIA BERSA CERRO COLORADO S.A. | E85: Cinergia Chile SpA | F85: ENEL DISTRIBUCIÓN CHILE S.A. | J85: 68.2376 | K85: 85.5939 | L85: 102.243 | M85: 114.0831 | N85: 136.773 | O85: 119.3695 | P85: 111.3834 | Q85: 111.0216 | R85: 126.0122
A86: INMOBILIARIA RENTAS II SPA | B86: A_DE_CORDOVA__013 | C86: 76179171-0 | D86: INMOBILIARIA RENTAS II SPA | E86: IMELSA_ENERGIA | F86: ENEL DISTRIBUCIÓN CHILE S.A. | G86: 483.40604 | H86: 425.48276 | I86: 455.59159 | J86: 411.38497 | K86: 401.87957 | L86: 422.44914 | M86: 435.54155 | N86: 406.4822 | O86: 377.05846 | P86: 390.66128 | Q86: 387.78049 | R86: 416.24911
A87: INMOBILIARIA Y CONSTRUCTORA ALONSO DE CORDOVA SPA | B87: A_DE_CORDOVA__013 | C87: 76182414-7 | D87: INMOBILIARIA Y CONSTRUCTORA ALONSO DE CORDOVA SPA | E87: ENEL_GENERACION | F87: ENEL DISTRIBUCIÓN CHILE S.A. | G87: 210.9546 | H87: 181.7775 | I87: 187.0702 | J87: 160.4147 | K87: 177.0257 | L87: 172.4562 | M87: 175.0268 | N87: 181.4647 | O87: 155.6416 | P87: 159.8868 | Q87: 165.8207 | R87: 182.8275
A88: INMOBILIARIA LOS MILITARES APOQUINDO SPA | B88: A_DE_CORDOVA__013 | C88: 76200792-4 | D88: INMOBILIARIA LOS MILITARES APOQUINDO SPA | E88: ENEL_GENERACION | F88: ENEL DISTRIBUCIÓN CHILE S.A. | G88: 210.4483 | H88: 181.24623 | I88: 181.8433 | J88: 174.51592 | K88: 159.01208 | L88: 179.10495 | M88: 169.71292 | N88: 159.96799 | O88: 145.57049 | P88: 157.0388 | Q88: 151.71353 | R88: 153.68099
A89: INMOBILIARIA Y CONSTRUCTORA NUEVOS TIEMPOS S.A | B89: A_DE_CORDOVA__013 | C89: 76203799-8 | D89: INMOBILIARIA Y CONSTRUCTORA NUEVOS TIEMPOS S.A | E89: GR Power Chile SpA | F89: ENEL DISTRIBUCIÓN CHILE S.A. | G89: 147.2938 | H89: 118.4462 | I89: 134.6304 | J89: 125.1817 | K89: 137.8012 | L89: 131.8013 | M89: 141.6547 | N89: 140.7685 | O89: 120.5246 | P89: 133.4119 | Q89: 130.6705 | R89: 137.612
A90: CONSTRUCTORA E INMOBILIARIA CIVITAS SPA | B90: A_DE_CORDOVA__013 | C90: 76238985-1 | D90: CONSTRUCTORA E INMOBILIARIA CIVITAS SPA | E90: COLBUN | F90: ENEL DISTRIBUCIÓN CHILE S.A. | G90: 85.44814 | H90: 75.32259 | I90: 78.56089 | J90: 67.43241 | K90: 68.97255 | L90: 75.83621 | M90: 78.83417 | N90: 76.27538 | O90: 75.9364 | P90: 81.94293 | Q90: 82.54641 | R90: 92.78803
A91: GLOBE POWER SPA | B91: A_DE_CORDOVA__013 | C91: 76301545-9 | D91: GLOBE POWER SPA | E91: IMELSA_ENERGIA | F91: ENEL DISTRIBUCIÓN CHILE S.A. | G91: 45.6047 | H91: 36.7584 | I91: 35.644 | J91: 33.4442 | K91: 35.4614 | L91: 37.2894 | M91: 39.9646 | N91: 36.4925 | O91: 31.8524 | P91: 35.1156 | Q91: 35.4967 | R91: 42.1318
A92: HOTELERA PATAGONIA DOS S.A. | B92: A_DE_CORDOVA__013 | C92: 76308711-5 | D92: HOTELERA PATAGONIA DOS S.A. | E92: COLBUN | F92: ENEL DISTRIBUCIÓN CHILE S.A. | G92: 254.7098 | H92: 224.8758 | I92: 224.0672
A93: HOTELERA PATAGONIA DOS S.A. | B93: A_DE_CORDOVA__013 | C93: 76308711-5 | D93: HOTELERA PATAGONIA DOS S.A. | E93: EMOAC | F93: ENEL DISTRIBUCIÓN CHILE S.A. | J93: 173.2272 | K93: 166.7388 | L93: 168.3362 | M93: 175.3312 | N93: 181.9333 | O93: 170.9211 | P93: 202.4593 | Q93: 210.1505 | R93: 238.845
A94: SOCIEDAD CONCESIONARIA VESPUCIO ORIENTE S.A. | B94: A_DE_CORDOVA__013 | C94: 76376061-8 | D94: SOCIEDAD CONCESIONARIA VESPUCIO ORIENTE S.A. | E94: EMOAC | F94: ENEL DISTRIBUCIÓN CHILE S.A. | G94: 218.25838 | H94: 170.51288 | I94: 182.33141 | J94: 162.48712 | K94: 167.76889 | L94: 192.00605 | M94: 194.0864 | N94: 205.06569 | O94: 188.32073 | P94: 193.33415 | Q94: 214.79582 | R94: 210.24594
A95: SOCIEDAD OPERADORA HOTELERA HA S.A | B95: A_DE_CORDOVA__013 | C95: 76470591-2 | D95: SOCIEDAD OPERADORA HOTELERA HA S.A | E95: SGA | F95: ENEL DISTRIBUCIÓN CHILE S.A. | G95: 85.50247 | H95: 70.54884 | I95: 67.14605 | J95: 56.0295 | K95: 56.80125 | L95: 54.05564 | M95: 58.80389 | N95: 56.25059 | O95: 54.34376 | P95: 56.28345 | Q95: 57.72767 | R95: 62.84151
A96: CONSTRUCTORA E INMOBILIARIA PRESIDENTE RIESCO S.A. | B96: A_DE_CORDOVA__013 | C96: 76493376-1 | D96: CONSTRUCTORA E INMOBILIARIA PRESIDENTE RIESCO S.A. | E96: COLBUN | F96: ENEL DISTRIBUCIÓN CHILE S.A. | J96: 67.4249 | K96: 92.5581 | L96: 117.2885 | M96: 130.3458 | N96: 124.2554 | O96: 110.6794 | P96: 110.2636 | Q96: 109.7712 | R96: 117.5999
A97: SOCIEDAD CONCESIONARIA COSTANERA NORTE S A | B97: A_DE_CORDOVA__013 | C97: 76496130-7 | D97: SOCIEDAD CONCESIONARIA COSTANERA NORTE S A | E97: ENEL_GENERACION | F97: ENEL DISTRIBUCIÓN CHILE S.A. | G97: 174.1185 | H97: 152.0941 | I97: 153.4894 | J97: 138.8714 | K97: 140.1547 | L97: 134.0878 | M97: 134.2349 | N97: 138.3496 | O97: 137.194 | P97: 149.5876 | Q97: 157.0637 | R97: 169.2686
A98: INMOBILIARIA BUSINESS PARK LIMITADA | B98: A_DE_CORDOVA__013 | C98: 76657840-3 | D98: INMOBILIARIA BUSINESS PARK LIMITADA | E98: IMELSA_ENERGIA | F98: ENEL DISTRIBUCIÓN CHILE S.A. | G98: 65.369 | H98: 62.598 | I98: 68.325 | J98: 54.502 | K98: 60.168 | L98: 82.633 | M98: 87.967 | N98: 74.844 | O98: 60.609 | P98: 52.597 | Q98: 54.328 | R98: 63.277
A99: INMOBILIARIA Y CONSTRUCTORA GERTRUDIS CALLAO SPA | B99: A_DE_CORDOVA__013 | C99: 76751838-2 | D99: INMOBILIARIA Y CONSTRUCTORA GERTRUDIS CALLAO SPA | E99: COLBUN | F99: ENEL DISTRIBUCIÓN CHILE S.A. | G99: 15.5315 | H99: 14.8515 | I99: 14.1893 | J99: 13.1326 | K99: 14.5782 | L99: 17.8375 | M99: 18.92 | N99: 20.3254 | O99: 20.1205 | P99: 24.8482 | Q99: 40.0552 | R99: 0
A100: INVERSIONES VIDA PARQUE S.A. | B100: A_DE_CORDOVA__013 | C100: 76834946-0 | D100: INVERSIONES VIDA PARQUE S.A. | E100: ENEL_GENERACION | F100: ENEL DISTRIBUCIÓN CHILE S.A. | G100: 335.182 | H100: 301.498 | I100: 333.676 | J100: 305.947 | K100: 306.298 | L100: 291.534 | M100: 293.53 | N100: 276.187 | O100: 243.96 | P100: 320.807 | Q100: 350.195 | R100: 369.537
A101: INMOBILIARIA ESPOZ SPA | B101: A_DE_CORDOVA__013 | C101: 76890772-2 | D101: INMOBILIARIA ESPOZ SPA | E101: PACIFIC HYDRO | F101: ENEL DISTRIBUCIÓN CHILE S.A. | H101: 7.0639 | I101: 16.7365 | J101: 14.4047 | K101: 26.5542 | L101: 40.5362 | M101: 50.3172 | N101: 46.4182 | O101: 35.1903 | P101: 33.999996 | Q101: 16.5084 | R101: 17.5943
A102: INMOBILIARIA LAS VIZCACHAS SPA | B102: A_DE_CORDOVA__013 | C102: 76908778-8 | D102: INMOBILIARIA LAS VIZCACHAS SPA | E102: IMELSA_ENERGIA | F102: ENEL DISTRIBUCIÓN CHILE S.A. | G102: 118.8165 | H102: 98.9089 | I102: 116.7876 | J102: 124.6148 | K102: 131.2064 | L102: 140.4742 | M102: 156.4828 | N102: 149.6306 | O102: 134.2298 | P102: 143.9316 | Q102: 131.0212 | R102: 128.016
A103: OPEN PLAZA CHILE SPA | B103: A_DE_CORDOVA__013 | C103: 77110043-0 | D103: OPEN PLAZA CHILE SPA | E103: ENEL_GENERACION | F103: ENEL DISTRIBUCIÓN CHILE S.A. | G103: 1371.2112 | H103: 1197.1164 | I103: 1248.7566 | J103: 1119.4886 | K103: 1113.4653 | L103: 1084.7661 | M103: 1113.6577 | N103: 1084.4594 | O103: 970.44351 | P103: 1037.8948 | Q103: 1026.1426 | R103: 575.02818
A104: SOCIEDAD CONCESIONARIA NUEVO PARQUE VITACURA SPA | B104: A_DE_CORDOVA__013 | C104: 77133707-4 | D104: SOCIEDAD CONCESIONARIA NUEVO PARQUE VITACURA SPA | E104: ENEL_GENERACION | F104: ENEL DISTRIBUCIÓN CHILE S.A. | G104: 60.0759 | H104: 46.8879 | I104: 61.5526 | J104: 55.2711 | K104: 54.0886 | L104: 49.6799 | M104: 48.8761 | N104: 64.2968 | O104: 65.6844 | P104: 76.5955 | Q104: 82.3985 | R104: 70.4419
A105: FALABELLA RETAIL S.A. | B105: A_DE_CORDOVA__013 | C105: 77261280-K | D105: FALABELLA RETAIL S.A. | E105: ENEL_GENERACION | F105: ENEL DISTRIBUCIÓN CHILE S.A. | G105: 271.85746 | H105: 223.88464 | I105: 234.67926 | J105: 203.58986 | K105: 186.19035 | L105: 163.83543 | M105: 191.50618 | N105: 204.02465 | O105: 195.62066 | P105: 225.62496 | Q105: 224.83704 | R105: 268.32533
A106: ADMINISTRADORA CASA C SPA | B106: A_DE_CORDOVA__013 | C106: 77465466-6 | D106: ADMINISTRADORA CASA C SPA | E106: EL_PINAR | F106: ENEL DISTRIBUCIÓN CHILE S.A. | R106: 578.6532
A107: ENEL X WAY CHILE SPA | B107: A_DE_CORDOVA__013 | C107: 77569067-4 | D107: ENEL X WAY CHILE SPA | E107: ENEL_GENERACION | F107: ENEL DISTRIBUCIÓN CHILE S.A. | G107: 72.3426 | H107: 58.596 | I107: 97.1337 | J107: 91.4732 | K107: 87.6077 | L107: 82.2339 | M107: 83.8544 | N107: 88.2837 | O107: 75.7297 | P107: 75.406 | Q107: 75.4706 | R107: 79.4347
...

Sheet Clientes Potencialmente Libres
B2: Clientes Regulados Potencialmente Libres a Diciembre 2025
B4: (Información entregada por las distribuidoras en el Catastro de Clientes Dx al que se refiere el artículo 1-17 de la Norma Técnica de Calidad de Servicio para Sistemas de Distribución)
B6: CONCESIONARIA | C6: CALIDAD JURIDICA | D6: TIPO_CLIENTE | E6: CLIENTE ID | F6: TIPO CONSUMO | G6: NOMBRE O RAZÓN SOCIAL DEL CLIENTE | H6: TIPO EMPALME | I6: TENSIÓN | J6: S/E PRIMARIA | K6: ALIMENTADOR | L6: POTENCIA_CONECTADA [kW] | M6: CONSUMO PROMEDIO ÚLTIMOS 12 MESES [kWh]
B7: CEC | D7: Cliente Potencialmente Libre | E7: 76145033 | F7: Industrial | G7: AGRICOLA EL MILAGRO LTDA. | H7: Red Aerea | I7: 0.38kV | J7: CURICO | K7: LOS NICHES | L7: 363 | M7: 7500
B8: CEC | D8: Cliente Potencialmente Libre | E8: 76145033 | F8: Industrial | G8: AGRICOLA EL MILAGRO LTDA. | H8: Red Aerea | I8: 0.38kV | J8: CURICO | K8: LOS NICHES | L8: 363 | M8: 1950
B9: CEC | D9: Cliente Potencialmente Libre | E9: 76145033 | F9: Industrial | G9: AGRICOLA EL MILAGRO LTDA. | H9: Red Aerea | I9: 0.38kV | J9: CURICO | K9: LOS NICHES | L9: 363 | M9: 2550
B10: CEC | D10: Cliente Potencialmente Libre | E10: 76152190 | F10: Industrial | G10: AGRICOLA EL PRINCIPAL LTDA | H10: Red Aerea | I10: 0.22kV | J10: CURICO | K10: LA OBRA | L10: 450 | M10: 3500
B11: CEC | D11: Cliente Potencialmente Libre | E11: 76152190 | F11: Industrial | G11: AGRICOLA EL PRINCIPAL LTDA | H11: Red Aerea | I11: 0.22kV | J11: CURICO | K11: LA OBRA | L11: 450 | M11: 3500
B12: CEC | D12: Cliente Potencialmente Libre | E12: 76152190 | F12: Industrial | G12: AGRICOLA EL PRINCIPAL LTDA | H12: Red Aerea | I12: 0.22kV | J12: CURICO | K12: LA OBRA | L12: 450 | M12: 2940
B13: CEC | D13: Cliente Potencialmente Libre | E13: 77980980 | F13: Industrial | G13: AGRICOLA GEOAGRO LIMITADA | H13: Red Aerea | I13: 0.38kV | J13: QUINTAY | K13: MORZA | L13: 451 | M13: 840
B14: CEC | D14: Cliente Potencialmente Libre | E14: 77980980 | F14: Industrial | G14: AGRICOLA GEOAGRO LIMITADA | H14: Red Aerea | I14: 0.38kV | J14: QUINTAY | K14: MORZA | L14: 451 | M14: 700
B15: CEC | D15: Cliente Potencialmente Libre | E15: 77980980 | F15: Industrial | G15: AGRICOLA GEOAGRO LIMITADA | H15: Red Aerea | I15: 0.38kV | J15: QUINTAY | K15: MORZA | L15: 451 | M15: 700
B16: CEC | D16: Cliente Potencialmente Libre | E16: 76599971 | F16: Agricola | G16: AGRICOLA RIBERA NORTE SPA | H16: Red Aerea | I16: 0.38kV | J16: TENO | K16: LA LAGUNA | L16: 850 | M16: 0
B17: CEC | D17: Cliente Potencialmente Libre | E17: 76599971 | F17: Agricola | G17: AGRICOLA RIBERA NORTE SPA | H17: Red Aerea | I17: 0.38kV | J17: TENO | K17: LA LAGUNA | L17: 850 | M17: 0
B18: CEC | D18: Cliente Potencialmente Libre | E18: 76599971 | F18: Agricola | G18: AGRICOLA RIBERA NORTE SPA | H18: Red Aerea | I18: 0.38kV | J18: TENO | K18: LA LAGUNA | L18: 850 | M18: 0
... B161: CEC | D161: Cliente Potencialmente Libre | E161: 77454128 | F161: Industrial | G161: YOLO GROUP SPA | H161: Red Aerea | I161: 0.22kV | J161: TENO | K161: LOS QUEÑES | L161: 728.7 | M161: 36929
B162: CGE | C162: Persona Jurídica | D162: Cliente Potencialmente Libre | E162: 78040440 | F162: Industrial | G162: PROEX SPA | H162: Red Aerea | I162: 15kV | J162: SAN FRANCISCO DE MOSTAZAL | K162: PILAY | L162: 389.7 | M162: 0
B163: CGE | C163: Persona Jurídica | D163: Cliente Potencialmente Libre | E163: 96858420 | F163: Agricola | G163: SOHO SPA | H163: Red Aerea | I163: 11kV | J163: HOSPITAL | K163: CHAMPA | L163: 498 | M163: 18760
B164: CGE | C164: Persona Jurídica | D164: Cliente Potencialmente Libre | E164: 65287570 | F164: Municipal | G164: 1RA BRIGADA ACORAZADA CORACEROS | H164: Red Aerea | I164: 0.38kV | J164: QUIANI | K164: CHUNGARA | L164: 592.3 | M164: 45000
B165: CGE | C165: Persona Jurídica | D165: Cliente Potencialmente Libre | E165: 65283230 | F165: Comercial | G165: 2 BRIGADA ACORAZADA CAZADORES | H165: Red Aerea | I165: 0.38kV | J165: POZO ALMONTE | K165: PAMPINO | L165: 592.3 | M165: 101400
B166: CGE | C166: Persona Jurídica | D166: Cliente Potencialmente Libre | E166: 65283230 | F166: Industrial | G166: 2 BRIGADA ACORAZADA CAZADORES | H166: Red Aerea | I166: 0.38kV | J166: POZO ALMONTE | K166: PAMPINO | L166: 329.1 | M166: 53880
B167: CGE | C167: Persona Jurídica | D167: Cliente Potencialmente Libre | E167: 76833720 | F167: Comercial | G167: ABARROTES ECONOMICOS LTDA. | H167: Red Aerea | I167: 0.38kV | J167: SAN CARLOS | K167: VIOLETA PARRA | L167: 329.1 | M167: 51000
B168: CGE | C168: Persona Jurídica | D168: Cliente Potencialmente Libre | E168: 76833720 | F168: Comercial | G168: ABARROTES ECONOMICOS LTDA. | H168: Red Aerea | I168: 15kV | J168: PERALES | K168: GOLONDRINAS | L168: 415.7 | M168: 35550
B169: CGE | C169: Persona Jurídica | D169: Cliente Potencialmente Libre | E169: 76833720 | F169: Comercial | G169: ABARROTES ECONOMICOS LTDA. | H169: Red Aerea | I169: 15kV | J169: PERALES | K169: GOLONDRINAS | L169: 415.7 | M169: 33900
B170: CGE | C170: Persona Jurídica | D170: Cliente Potencialmente Libre | E170: 76833720 | F170: Comercial | G170: ABARROTES ECONOMICOS LTDA. | H170: Red Aerea | I170: 12 kV | J170: SANTA ROSA SUR | K170: LO MARTINEZ | L170: 311.8 | M170: 0
B171: CGE | C171: Persona Jurídica | D171: Cliente Potencialmente Libre | E171: 76833720 | F171: Residencial | G171: ABARROTES ECONOMICOS LTDA. | H171: Red Aerea | I171: 15kV | J171: CHIGUAYANTE | K171: HUALQUI | L171: 311.8 | M171: 36000
B172: CGE | C172: Persona Jurídica | D172: Cliente Potencialmente Libre | E172: 76833720 | F172: Comercial | G172: ABARROTES ECONOMICOS LTDA. | H172: Red Aerea | I172: 0.38kV | J172: CONSTITUCION | K172: FALUCHO | L172: 329.1 | M172: 51360
B173: CGE | C173: Persona Jurídica | D173: Cliente Potencialmente Libre | E173: 76833720 | F173: Comercial | G173: ABARROTES ECONOMICOS LTDA. | H173: Red Aerea | I173: 15kV | J173: LAS ENCINAS | K173: BOTROLHUE | L173: 389.7 | M173: 32700
... B223: CGE | C223: Persona Jurídica | D223: Cliente Potencialmente Libre | E223: 96549220 | F223: Comercial | G223: AGRI Y COMER STA CECILIA S.A. | H223: Red Aerea | I223: 15kV | J223: MANSO DE VELASCO | K223: ALEMANIA | L223: 311.8 | M223: 8700
B224: CGE | C224: Persona Jurídica | D224: Cliente Potencialmente Libre | E224: 78058290 | F224: Agricola | G224: AGRIC LA CABAÑA DOS LTDA | H224: Red Aerea | I224: 15kV | L224: 311.8 | M224: 50778
B225: CGE | C225: Persona Jurídica | D225: Cliente Potencialmente Libre | E225: 77865980 | F225: Agricola | G225: AGRIC STA CRISTINA LTDA | H225: Red Aerea | I225: 15kV | J225: CHUMAQUITO | K225: SAN ISIDRO | L225: 415.7 | M225: 9450
B226: CGE | C226: Persona Jurídica | D226: Cliente Potencialmente Libre | E226: 76069280 | F226: Agricola | G226: AGRIC Y EXP.TIERRA PURA LIMITADA | H226: Red Aerea | I226: 23kV | J226: INCAHUASI | K226: LA HIGUERA | L226: 637.4 | M226: 1920
B227: CGE | C227: Persona Jurídica | D227: Cliente Potencialmente Libre | E227: 89139200 | F227: Comercial | G227: AGRIC Y FRUTICOLA DEL CENTRO LTDA | H227: Red Aerea | I227: 0.38kV | J227: VILLA PRAT | K227: PETEROA | L227: 329.1 | M227: 16800
B228: CGE | C228: Persona Jurídica | D228: Cliente Potencialmente Libre | E228: 89139200 | F228: Industrial | G228: AGRIC Y FRUTICOLA DEL CENTRO LTDA | H228: Red Aerea | I228: 13kV | J228: CURICO | K228: ZAPALLAR | L228: 731.6 | M228: 1920
B229: CGE | C229: Persona Jurídica | D229: Cliente Potencialmente Libre | E229: 77587720 | F229: Agricola | G229: AGRIC. EL BUEN PASTOR LTDA | H229: Red Aerea | I229: 15kV | J229: COLCHAGUA | K229: TINGUIRIRICA | L229: 1636.7 | M229: 23775
B230: CGE | C230: Persona Jurídica | D230: Cliente Potencialmente Libre | E230: 77373640 | F230: Agricola | G230: AGRÍC. FORESTAL Y GANADERA STA INES DE | H230: Red Aerea | I230: 15kV | J230: LEYDA | K230: EL TURCO | L230: 311.8 | M230: 69720
B231: CGE | C231: Persona Jurídica | D231: Cliente Potencialmente Libre | E231: 77373640 | F231: Agricola | G231: AGRÍC. FORESTAL Y GANADERA STA INES DE | H231: Red Aerea | I231: 15kV | J231: LEYDA | K231: EL TURCO | L231: 311.8 | M231: 95480
B232: CGE | C232: Persona Jurídica | D232: Cliente Potencialmente Libre | E232: 78750450 | F232: Agricola | G232: AGRIC. GREEN SEED LTDA. | H232: Red Aerea | I232: 0.38kV | J232: SAN FRANCISCO DE MOSTAZAL | K232: SANTA BLANCA | L232: 329.1 | M232: 6600
B233: CGE | C233: Persona Jurídica | D233: Cliente Potencialmente Libre | E233: 84629300 | F233: Agricola | G233: AGRICOLA AGROBOSQUES SAN ISIDRO SA | H233: Red Aerea | I233: 15kV | J233: GRANEROS | K233: BERRIOS | L233: 415.7 | M233: 9600
B234: CGE | C234: Persona Jurídica | D234: Cliente Potencialmente Libre | E234: 84629300 | F234: Agricola | G234: AGRICOLA AGROBOSQUES SAN ISIDRO SA | H234: Red Aerea | I234: 15kV | J234: GRANEROS | K234: BERRIOS | L234: 415.7 | M234: 23400
B235: CGE | C235: Persona Jurídica | D235: Cliente Potencialmente Libre | E235: 79524840 | F235: Agricola | G235: AGRICOLA AGROPAL LTDA | H235: Red Aerea | I235: 23kV | J235: OVALLE | K235: HOSPITAL | L235: 796.7 | M235: 26058
B236: CGE | C236: Persona Jurídica | D236: Cliente Potencialmente Libre | E236: 79524840 | F236: Industrial | G236: AGRICOLA AGROPAL LTDA | H236: Red Aerea | I236: 23kV | J236: OVALLE | K236: RECOLETA | L236: 318.7 | M236: 6960
... B330: CGE | C330: Persona Jurídica | D330: Cliente Potencialmente Libre | E330: 76037687 | F330: Agricola | G330: AGRICOLA PRAVIA S. A. | H330: Red Aerea | I330: 13kV | J330: LIHUEIMO | K330: ARBOLEDA | L330: 1714.7 | M330: 6975
B331: CGE | C331: Persona Jurídica | D331: Cliente Potencialmente Libre | E331: 76125892 | F331: Industrial | G331: AGRICOLA PULMODON LIMITADA | H331: Red Aerea | I331: 0.38kV | L331: 362 | M331: 3640
B332: CGE | C332: Persona Jurídica | D332: Cliente Potencialmente Libre | E332: 76125892 | F332: Industrial | G332: AGRICOLA PULMODON LIMITADA | H332: Red Aerea | I332: 0.38kV | L332: 362 | M332: 9520
B333: CGE | C333: Persona Jurídica | D333: Cliente Potencialmente Libre | E333: 76989087 | F333: Comercial | G333: AGRÍCOLA QUIAHUE | H333: Red Aerea | I333: 13kV | J333: RANGUILI | K333: PAREDONES | L333: 685.9 | M333: 79500
B334: CGE | C334: Persona Jurídica | D334: Cliente Potencialmente Libre | E334: 76989087 | F334: Comercial | G334: AGRÍCOLA QUIAHUE | H334: Red Aerea | I334: 13kV | J334: RANGUILI | K334: PAREDONES | L334: 685.9 | M334: 44400
B335: CGE | C335: Persona Jurídica | D335: Cliente Potencialmente Libre | E335: 79555510 | F335: Agricola | G335: AGRICOLA RAMADILLA LTDA | H335: Red Aerea | I335: 0.38kV | J335: MARCHIGUE | K335: LA ESTRELLA | L335: 329.1 | M335: 32130
B336: CGE | C336: Persona Jurídica | D336: Cliente Potencialmente Libre | E336: 77475270 | F336: Comercial | G336: AGRICOLA RINCONADA DE LOS ALAMOS S.A. | H336: Red Aerea | I336: 15kV | J336: ALAMEDA | K336: REPUBLICA DE CHILE | L336: 1636.7 | M336: 5775
B337: CGE | C337: Persona Jurídica | D337: Cliente Potencialmente Libre | E337: 79697820 | F337: Agricola | G337: AGRICOLA RIO EL TRANSITO LTDA | H337: Red Aerea | I337: 13kV | J337: ALTO DEL CARMEN | K337: EL TRANSITO | L337: 457.3 | M337: 840
B338: CGE | C338: Persona Jurídica | D338: Cliente Potencialmente Libre | E338: 76257275 | F338: Agricola | G338: AGRICOLA ROBLEDAL LTDA | H338: Red Aerea | I338: 13kV | J338: BAJO MELIPILLA | K338: HUECHUN | L338: 717.1 | M338: 12900
B339: CGE | C339: Persona Jurídica | D339: Cliente Potencialmente Libre | E339: 76257275 | F339: Agricola | G339: AGRICOLA ROBLEDAL LTDA | H339: Red Aerea | I339: 13kV | J339: BAJO MELIPILLA | K339: HUECHUN | L339: 717.1 | M339: 11700
B340: CGE | C340: Persona Jurídica | D340: Cliente Potencialmente Libre | E340: 76829801 | F340: Agricola | G340: AGRICOLA S G | H340: Red Aerea | I340: 13kV | J340: SANTA CRUZ | K340: PALMILLA | L340: 914.5 | M340: 3439
B341: CGE | C341: Persona Jurídica | D341: Cliente Potencialmente Libre | E341: 76829801 | F341: Agricola | G341: AGRICOLA S G | H341: Red Aerea | I341: 13kV | J341: SANTA CRUZ | K341: PALMILLA | L341: 914.5 | M341: 1885
B342: CGE | C342: Persona Jurídica | D342: Cliente Potencialmente Libre | E342: 78261820 | F342: Industrial | G342: AGRICOLA SAN ANTONIO LTDA. | H342: Red Aerea | I342: 15kV | J342: CHACAHUIN | K342: PRESIDENTE IBAÑEZ | L342: 389.7 | M342: 36600
B343: CGE | C343: Persona Jurídica | D343: Cliente Potencialmente Libre | E343: 78063330 | F343: Agricola | G343: AGRICOLA SAN BERNARDO LTDA | H343: Red Aerea | I343: 11kV | J343: MALLOCO | K343: MANUEL CASTILLO | L343: 318.7 | M343: 6750
B344: CGE | C344: Persona Jurídica | D344: Cliente Potencialmente Libre | E344: 77254755 | F344: Agricola | G344: AGRICOLA SAN CARLOS DE PAIHUEN LIMITADA | H344: Red Aerea | I344: 23kV | J344: CABILDO | K344: ALICAHUE | L344: 318.7 | M344: 0
... B408: CGE | C408: Persona Jurídica | D408: Cliente Potencialmente Libre | E408: 88680500 | F408: Agricola | G408: AGRICOLA SUPER LTDA. | H408: Red Aerea | I408: 13kV | J408: SAN FRANCISCO DE MOSTAZAL | K408: PILAY | L408: 342.9 | M408: 3150
B409: CGE | C409: Persona Jurídica | D409: Cliente Potencialmente Libre | E409: 88680500 | F409: Agricola | G409: AGRICOLA SUPER LTDA. | H409: Red Aerea | I409: 15kV | L409: 311.8 | M409: 4050
B410: CGE | C410: Persona Jurídica | D410: Cliente Potencialmente Libre | E410: 88680500 | F410: Agricola | G410: AGRICOLA SUPER LTDA. | H410: Red Aerea | I410: 12 kV | J410: CURACAVI | K410: CURACAVI | L410: 311.8 | M410: 62550
B411: CGE | C411: Persona Jurídica | D411: Cliente Potencialmente Libre | E411: 88680500 | F411: Agricola | G411: AGRICOLA SUPER LTDA. | H411: Red Aerea | I411: 12 kV | J411: CURACAVI | K411: CURACAVI | L411: 311.8 | M411: 24300
B412: CGE | C412: Persona Jurídica | D412: Cliente Potencialmente Libre | E412: 89025500 | F412: Industrial | G412: AGRICOLA TENQUELEN S.A. | H412: Red Aerea | I412: 0.38kV | J412: NANCAGUA | K412: NANCAGUA | L412: 329.1 | M412: 10500
B413: CGE | C413: Persona Jurídica | D413: Cliente Potencialmente Libre | E413: 89025500 | F413: Industrial | G413: AGRICOLA TENQUELEN S.A. | H413: Red Aerea | I413: 0.38kV | J413: NANCAGUA | K413: NANCAGUA | L413: 329.1 | M413: 10500
B414: CGE | C414: Persona Jurídica | D414: Cliente Potencialmente Libre | E414: 79534860 | F414: Agricola | G414: AGRICOLA U.A.C. LTDA. | H414: Red Aerea | I414: 0.38kV | J414: LOS LOROS | K414: AMOLANAS | L414: 394.9 | M414: 24480
B415: CGE | C415: Persona Jurídica | D415: Cliente Potencialmente Libre | E415: 79602650 | F415: Agricola | G415: AGRICOLA UNIAGRI COPIAPO SPA | H415: Red Aerea | I415: 15kV | J415: HOSPITAL | K415: CHALLAY | L415: 519.6 | M415: 52650
B416: CGE | C416: Persona Jurídica | D416: Cliente Potencialmente Libre | E416: 79602650 | F416: Agricola | G416: AGRICOLA UNIAGRI COPIAPO SPA | H416: Red Aerea | I416: 15kV | J416: HOSPITAL | K416: CHALLAY | L416: 519.6 | M416: 59400
B417: CGE | C417: Persona Jurídica | D417: Cliente Potencialmente Libre | E417: 79602640 | F417: Agricola | G417: AGRICOLA UNIAGRI OVALLE SPA | H417: Red Aerea | I417: 12 kV | J417: MONTE PATRIA | K417: EL PALQUI | L417: 311.8 | M417: 20440
B418: CGE | C418: Persona Jurídica | D418: Cliente Potencialmente Libre | E418: 79602640 | F418: Agricola | G418: AGRICOLA UNIAGRI OVALLE SPA | H418: Red Aerea | I418: 0.38kV | J418: HERNAN FUENTES | K418: PIEDRA COLGADA | L418: 592.3 | M418: 22800
B419: CGE | C419: Persona Jurídica | D419: Cliente Potencialmente Libre | E419: 76532858 | F419: Comercial | G419: AGRICOLA URSULA SPA | H419: Red Aerea | I419: 12 kV | L419: 332.5 | M419: 9900
B420: CGE | C420: Persona Jurídica | D420: Cliente Potencialmente Libre | E420: 76532858 | F420: Comercial | G420: AGRICOLA URSULA SPA | H420: Red Aerea | I420: 12 kV | L420: 311.8 | M420: 14250
B421: CGE | C421: Persona Jurídica | D421: Cliente Potencialmente Libre | E421: 76163570 | F421: Agricola | G421: AGRICOLA VALLE ALTO LTDA | H421: Red Aerea | I421: 23kV | J421: VICUÑA | K421: RIVADAVIA | L421: 368 | M421: 61680
B422: CGE | C422: Persona Jurídica | D422: Cliente Potencialmente Libre | E422: 76163570 | F422: Agricola | G422: AGRICOLA VALLE ALTO LTDA | H422: Red Aerea | I422: 23kV | J422: VICUÑA | K422: RIVADAVIA | L422: 368 | M422: 75600
B423: CGE | C423: Persona Jurídica | D423: Cliente Potencialmente Libre | E423: 96807590 | F423: Agricola | G423: AGRICOLA VESPUCIO S.A. | H423: Red Aerea | I423: 23kV | J423: MONTE PATRIA | K423: SAN LORENZO | L423: 398.4 | M423: 29520
B424: CGE | C424: Persona Jurídica | D424: Cliente Potencialmente Libre | E424: 76360601 | F424: Comercial | G424: AGRICOLA VIEJO NERQUIHUE | H424: Red Aerea | I424: 13kV | J424: SANTA CRUZ | K424: LOLOL | L424: 2857.8 | M424: 844
B425: CGE | C425: Persona Jurídica | D425: Cliente Potencialmente Libre | E425: 78105000 | F425: Agricola | G425: AGRICOLA VIZCAYA LTDA | H425: Red Aerea | I425: 15kV | J425: RENGO | K425: ESMERALDA | L425: 649.5 | M425: 76800
B426: CGE | C426: Persona Jurídica | D426: Cliente Potencialmente Libre | E426: 77576239 | F426: Residencial | G426: AGRICOLA VOLANTIN LTDA | H426: Red Aerea | I426: 15kV | J426: LAS CABRAS | K426: COCALAN | L426: 1039.2 | M426: 0
B427: CGE | C427: Persona Jurídica | D427: Cliente Potencialmente Libre | E427: 76306692 | F427: Agricola | G427: AGRÍCOLA WEINBERG LIMITADA | H427: Red Aerea | I427: 13kV | J427: CURICO | K427: MATAQUITO | L427: 1440.3 | M427: 3337
B428: CGE | C428: Persona Jurídica | D428: Cliente Potencialmente Libre | E428: 76055147 | F428: Agricola | G428: AGRICOLA Y COMERCIAL FIUME S.A. | H428: Red Aerea | I428: 12 kV | J428: SAN BERNARDO | K428: LAS PALMERAS | L428: 332.5 | M428: 19500
B429: CGE | C429: Persona Jurídica | D429: Cliente Potencialmente Libre | E429: 76055147 | F429: Agricola | G429: AGRICOLA Y COMERCIAL FIUME S.A. | H429: Red Aerea | I429: 12 kV | J429: SAN BERNARDO | K429: LAS PALMERAS | L429: 332.5 | M429: 17100
B430: CGE | C430: Persona Jurídica | D430: Cliente Potencialmente Libre | E430: 96516320 | F430: Comercial | G430: AGRICOLA Y COMERCIAL LIRCAY S.A. | H430: Red Aerea | I430: 15kV | J430: SAN MIGUEL | K430: SAN CLEMENTE | L430: 311.8 | M430: 71700
B431: CGE | C431: Persona Jurídica | D431: Cliente Potencialmente Libre | E431: 96649100 | F431: Agricola | G431: AGRICOLA Y COMERCIAL SANTA CAMILA S.A. | H431: Red Aerea | I431: 13kV | J431: LA ESPERANZA | K431: LOS OLIVOS | L431: 342.9 | M431: 420
B432: CGE | C432: Persona Jurídica | D432: Cliente Potencialmente Libre | E432: 96649100 | F432: Agricola | G432: AGRICOLA Y COMERCIAL SANTA CAMILA S.A. | H432: Red Aerea | I432: 13kV | J432: LA ESPERANZA | K432: LOS OLIVOS | L432: 342.9 | M432: 420
B433: CGE | C433: Persona Jurídica | D433: Cliente Potencialmente Libre | E433: 96649100 | F433: Industrial | G433: AGRICOLA Y COMERCIAL SANTA CAMILA S.A. | H433: Red Aerea | I433: 0.38kV | L433: 329.1 | M433: 11714
B434: CGE | C434: Persona Jurídica | D434: Cliente Potencialmente Libre | E434: 79736000 | F434: Agricola | G434: AGRICOLA Y GANADERA CABEZA NEGRA | H434: Red Aerea | I434: 13kV | J434: LOS MAQUIS | K434: LOS ROBLES | L434: 1371.7 | M434: 14840
B435: CGE | C435: Persona Jurídica | D435: Cliente Potencialmente Libre | E435: 79736000 | F435: Agricola | G435: AGRICOLA Y GANADERA CABEZA NEGRA | H435: Red Aerea | I435: 0.38kV | J435: LOS MAQUIS | K435: LOS ROBLES | L435: 329.1 | M435: 1307
B436: CGE | C436: Persona Jurídica | D436: Cliente Potencialmente Libre | E436: 78400010 | F436: Agricola | G436: AGRICOLA Y GANADERA STA BARBARA LTDA | H436: Red Aerea | I436: 13kV | J436: RAUQUEN | K436: QUILVO | L436: 342.9 | M436: 7420
B437: CGE | C437: Persona Jurídica | D437: Cliente Potencialmente Libre | E437: 78400010 | F437: Agricola | G437: AGRICOLA Y GANADERA STA BARBARA LTDA | H437: Red Aerea | I437: 13kV | J437: RAUQUEN | K437: QUILVO | L437: 342.9 | M437: 16380
B438: CGE | C438: Persona Jurídica | D438: Cliente Potencialmente Libre | E438: 79641420 | F438: Agricola | G438: AGRICOLA Y TRANSPORTES LAS ACACIAS LIMIT | H438: Red Aerea | I438: 13kV | J438: CHIMBARONGO | K438: SAN ENRIQUE | L438: 1440.3 | M438: 835
B439: CGE | C439: Persona Jurídica | D439: Cliente Potencialmente Libre | E439: 76418949 | F439: Agricola | G439: AGRICOLA ZURIA LIMITADA | H439: Red Aerea | I439: 15kV | J439: COLCHAGUA | K439: TINGUIRIRICA | L439: 389.7 | M439: 24480
B440: CGE | C440: Persona Jurídica | D440: Cliente Potencialmente Libre | E440: 76418949 | F440: Agricola | G440: AGRICOLA ZURIA LIMITADA | H440: Red Aerea | I440: 15kV | J440: COLCHAGUA | K440: TINGUIRIRICA | L440: 389.7 | M440: 1800
B441: CGE | C441: Persona Jurídica | D441: Cliente Potencialmente Libre | E441: 96993240 | F441: Agricola | G441: AGRICOVIAL S.A. | H441: Red Aerea | I441: 12 kV | J441: SAN BERNARDO | K441: BARRANCON | L441: 332.5 | M441: 90300
B442: CGE | C442: Persona Jurídica | D442: Cliente Potencialmente Libre | E442: 96993240 | F442: Agricola | G442: AGRICOVIAL S.A. | H442: Red Aerea | I442: 12 kV | J442: SAN BERNARDO | K442: BARRANCON | L442: 332.5 | M442: 91950
B443: CGE | C443: Persona Jurídica | D443: Cliente Potencialmente Libre | E443: 78422300 | F443: Agricola | G443: AGRO COMERCIAL LAS TINAJAS LTDA | H443: Red Aerea | I443: 15kV | J443: PELEQUEN | K443: SANTA ROSA | L443: 519.6 | M443: 18900
B444: CGE | C444: Persona Jurídica | D444: Cliente Potencialmente Libre | E444: 77620020 | F444: Comercial | G444: AGRO COMERCIAL TERRAMAR CHILE | H444: Red Aerea | I444: 15kV | J444: ESCUADRON | K444: CARBONIFERA | L444: 415.7 | M444: 7500
B445: CGE | C445: Persona Jurídica | D445: Cliente Potencialmente Libre | E445: 77620020 | F445: Comercial | G445: AGRO COMERCIAL TERRAMAR CHILE | H445: Red Aerea | I445: 15kV | J445: ESCUADRON | K445: CARBONIFERA | L445: 415.7 | M445: 8100
... B504: CGE | C504: Persona Jurídica | D504: Cliente Potencialmente Libre | E504: 76418976 | F504: Comercial | G504: AGUAS DE ANTOFAGASTA S.A. | H504: Red Aerea | I504: 13kV | J504: CENTRO | K504: ALBERTO HURTADO | L504: 478 | M504: 35850
B505: CGE | C505: Persona Jurídica | D505: Cliente Potencialmente Libre | E505: 76418976 | F505: Comercial | G505: AGUAS DE ANTOFAGASTA S.A. | H505: Red Aerea | I505: 23kV | L505: 318.7 | M505: 145080
B506: CGE | C506: Persona Jurídica | D506: Cliente Potencialmente Libre | E506: 76215634 | F506: Comercial | G506: AGUAS DEL ALTIPLANO S.A. | H506: Red Aerea | I506: 0.38kV | J506: CHINCHORRO | K506: INDUSTRIAL | L506: 329.1 | M506: 45750
B507: CGE | C507: Persona Jurídica | D507: Cliente Potencialmente Libre | E507: 76215634 | F507: Comercial | G507: AGUAS DEL ALTIPLANO S.A. | H507: Red Aerea | I507: 13kV | J507: PUKARA | K507: PORTALES | L507: 571.6 | M507: 12372
B508: CGE | C508: Persona Jurídica | D508: Cliente Potencialmente Libre | E508: 76215634 | F508: Industrial | G508: AGUAS DEL ALTIPLANO S.A. | H508: Red Aerea | I508: 0.38kV | J508: POZO ALMONTE | K508: PAMPINO | L508: 329.1 | M508: 46560
...

Sheet Escondida
A2: =+"Consumo de Clientes Libres en Balance de Transferencias de Energía (valores en MWh) en últimos 12 meses" -> Consumo de Clientes Libres en Balance de Transferencias de Energía (valores en MWh) en últimos 12 meses
B4: BARRA | C4: RUT CLIENTE | D4: NOMBRE O RAZÓN SOCIAL DEL CLIENTE | E4: SUMINISTRADOR | F4: CONECTADO A LA RED DE | G4: ene-25 | H4: feb-25 | I4: mar-25 | J4: abr-25 | K4: may-25 | L4: jun-25 | M4: jul-25 | N4: ago-25 | O4: sept-25 | P4: oct-25 | Q4: nov-25 | R4: dic-25 | T4: TOTAL
A5: {=_xlfn._xlws.FILTER('Clientes Libres'!$A$5:$R$5414,'Clientes Libres'!$A$5:$A$5414="MINERA ESCONDIDA LIMITADA")} -> MINERA ESCONDIDA LIMITADA | B5: BOMBEO2_______004 | C5: 79587210-8 | D5: MINERA ESCONDIDA LIMITADA | E5: COLBUN | F5: Cliente AT | G5: 460.29815 | H5: 393.69743 | I5: 455.07673 | J5: 544.58101 | K5: 608.62649 | L5: 442.8749 | M5: 604.66289 | N5: 573.45262 | O5: 527.31077 | P5: 536.18789 | Q5: 367.59233 | R5: 357.50604 | T5: =SUM(G5:R5) -> 5871.8673
A6: MINERA ESCONDIDA LIMITADA | B6: BOMBEO2_______004 | C6: 79587210-8 | D6: MINERA ESCONDIDA LIMITADA | E6: ENEL_GENERACION | F6: Cliente AT | G6: 499.73655 | H6: 393.63644 | I6: 458.99249 | J6: 544.48846 | K6: 608.3669 | L6: 442.11346 | M6: 604.55423 | N6: 573.42608 | O6: 527.27819 | P6: 536.18789 | Q6: 367.59233 | R6: 320.10306 | T6: =SUM(G6:R6) -> 5876.4761
A7: MINERA ESCONDIDA LIMITADA | B7: BOMBEO2_______004 | C7: 79587210-8 | D7: MINERA ESCONDIDA LIMITADA | E7: TAMAKAYA_ENERGIA | F7: Cliente AT | G7: 0 | H7: 0 | I7: 3.960167 | J7: 0 | K7: 0 | L7: 0 | M7: 0 | N7: 0.026543 | O7: 0.032583 | P7: 0 | Q7: 0 | R7: 249.35575 | T7: =SUM(G7:R7) -> 253.37505
A8: MINERA ESCONDIDA LIMITADA | B8: BOMBEO3_______004 | C8: 79587210-8 | D8: MINERA ESCONDIDA LIMITADA | E8: COLBUN | F8: Cliente AT | G8: 557.59304 | H8: 511.68874 | I8: 530.61945 | J8: 610.34706 | K8: 588.06084 | L8: 424.45912 | M8: 596.63574 | N8: 678.24684 | O8: 659.43974 | P8: 635.00167 | Q8: 481.69758 | R8: 367.1744 | T8: =SUM(G8:R8) -> 6640.9642
A9: MINERA ESCONDIDA LIMITADA | B9: BOMBEO3_______004 | C9: 79587210-8 | D9: MINERA ESCONDIDA LIMITADA | E9: ENEL_GENERACION | F9: Cliente AT | G9: 605.90996 | H9: 511.61375 | I9: 537.3255 | J9: 610.25985 | K9: 587.81773 | L9: 423.70488 | M9: 596.5159 | N9: 678.22042 | O9: 659.40725 | P9: 635.00167 | Q9: 481.69758 | R9: 322.04701 | T9: =SUM(G9:R9) -> 6649.5215
A10: MINERA ESCONDIDA LIMITADA | B10: BOMBEO3_______004 | C10: 79587210-8 | D10: MINERA ESCONDIDA LIMITADA | E10: TAMAKAYA_ENERGIA | F10: Cliente AT | G10: 0 | H10: 0 | I10: 6.766437 | J10: 0 | K10: 0 | L10: 0 | M10: 0 | N10: 0.026418 | O10: 0.03249 | P10: 0 | Q10: 0 | R10: 282.92906 | T10: =SUM(G10:R10) -> 289.7544
A11: MINERA ESCONDIDA LIMITADA | B11: BOMBEO4_______004 | C11: 79587210-8 | D11: MINERA ESCONDIDA LIMITADA | E11: COLBUN | F11: Cliente AT | G11: 581.28291 | H11: 494.92721 | I11: 537.84914 | J11: 633.89743 | K11: 612.67975 | L11: 428.98917 | M11: 590.02888 | N11: 599.63951 | O11: 589.31599 | P11: 589.06608 | Q11: 443.28045 | R11: 330.67957 | T11: =SUM(G11:R11) -> 6431.6361
A12: MINERA ESCONDIDA LIMITADA | B12: BOMBEO4_______004 | C12: 79587210-8 | D12: MINERA ESCONDIDA LIMITADA | E12: ENEL_GENERACION | F12: Cliente AT | G12: 631.63555 | H12: 494.85621 | I12: 544.80693 | J12: 633.80362 | K12: 612.4277 | L12: 428.20497 | M12: 589.90588 | N12: 599.61667 | O12: 589.28819 | P12: 589.06608 | Q12: 443.28045 | R12: 289.09101 | T12: =SUM(G12:R12) -> 6445.9833
A13: MINERA ESCONDIDA LIMITADA | B13: BOMBEO4_______004 | C13: 79587210-8 | D13: MINERA ESCONDIDA LIMITADA | E13: TAMAKAYA_ENERGIA | F13: Cliente AT | G13: 0 | H13: 0 | I13: 7.018365 | J13: 0 | K13: 0 | L13: 0 | M13: 0 | N13: 0.022843 | O13: 0.027804 | P13: 0 | Q13: 0 | R13: 266.55605 | T13: =SUM(G13:R13) -> 273.62507
A14: MINERA ESCONDIDA LIMITADA | B14: CHIMBORAZO____220 | C14: 79587210-8 | D14: MINERA ESCONDIDA LIMITADA | E14: COLBUN | F14: Cliente AT | G14: 13086.623 | H14: 13239.782 | I14: 13681.745 | J14: 14402.74 | K14: 15258.894 | L14: 13559.136 | M14: 12532.263 | N14: 13184.597 | O14: 13603.579 | P14: 14103.642 | Q14: 12527.713 | R14: 12927.946 | T14: =SUM(G14:R14) -> 162108.66
A15: MINERA ESCONDIDA LIMITADA | B15: CHIMBORAZO____220 | C15: 79587210-8 | D15: MINERA ESCONDIDA LIMITADA | E15: ENEL_GENERACION | F15: Cliente AT | G15: 14182.392 | H15: 13238.252 | I15: 13818.423 | J15: 14400.65 | K15: 15253.17 | L15: 13540.831 | M15: 12529.673 | N15: 13184.068 | O15: 13602.913 | P15: 14103.642 | Q15: 12527.713 | R15: 10980.383 | T15: =SUM(G15:R15) -> 161362.11
A16: MINERA ESCONDIDA LIMITADA | B16: CHIMBORAZO____220 | C16: 79587210-8 | D16: MINERA ESCONDIDA LIMITADA | E16: TAMAKAYA_ENERGIA | F16: Cliente AT | G16: 0 | H16: 0 | I16: 138.01374 | J16: 0 | K16: 0 | L16: 0 | M16: 0 | N16: 0.52921 | O16: 0.666506 | P16: 0 | Q16: 0 | R16: 7482.7234 | T16: =SUM(G16:R16) -> 7621.9329
A17: MINERA ESCONDIDA LIMITADA | B17: COLOSO________220 | C17: 79587210-8 | D17: MINERA ESCONDIDA LIMITADA | E17: COLBUN | F17: Cliente AT | G17: 27899.808 | H17: 28132.644 | I17: 29700.716 | J17: 31341.929 | K17: 32580.186 | L17: 28704.892 | M17: 26995.389 | N17: 28625.258 | O17: 29135.405 | P17: 30085.344 | Q17: 26910.737 | R17: 25671.884 | T17: =SUM(G17:R17) -> 345784.19
... A38: MINERA ESCONDIDA LIMITADA | B38: SUR___________110 | C38: 79587210-8 | D38: MINERA ESCONDIDA LIMITADA | E38: AES_GENER | F38: COMPAÑÍA GENERAL DE ELECTRICIDAD S.A. | G38: 0 | H38: 0 | I38: 0 | J38: 0 | K38: 0 | L38: 0 | M38: 0 | N38: 0 | O38: 0 | P38: 0 | Q38: 0 | R38: 0 | T38: =SUM(G38:R38) -> 0
G40: =SUM(G5:G38) -> 448230.51 | H40: =SUM(H5:H38) -> 431099.76 | I40: =SUM(I5:I38) -> 470673.5 | J40: =SUM(J5:J38) -> 491152.01 | K40: =SUM(K5:K38) -> 509202.61 | L40: =SUM(L5:L38) -> 461526.09 | M40: =SUM(M5:M38) -> 458204.33 | N40: =SUM(N5:N38) -> 482092.66 | ... R40: =SUM(R5:R38) -> 496969.65 | T40: =SUM(T5:T38) -> 5629455

Sheet Locations
B1: Barra | C1: Tipo | D1: ene-25 | E1: feb-25 | F1: mar-25 | G1: abr-25 | H1: may-25 | I1: jun-25 | J1: jul-25 | K1: ago-25 | L1: sept-25 | M1: oct-25 | N1: nov-25 | O1: dic-25 | P1: TOTAL
B2: BOMBEO2_______004 | C2: Bombeo | D2: =SUMIF(Escondida!$B$5:$B$38,Locations!$B2,Escondida!G$5:G$38) -> 960.03469 | E2: =SUMIF(Escondida!$B$5:$B$38,Locations!$B2,Escondida!H$5:H$38) -> 787.33388 | F2: =SUMIF(Escondida!$B$5:$B$38,Locations!$B2,Escondida!I$5:I$38) -> 918.02939 | G2: =SUMIF(Escondida!$B$5:$B$38,Locations!$B2,Escondida!J$5:J$38) -> 1089.0695 | H2: =SUMIF(Escondida!$B$5:$B$38,Locations!$B2,Escondida!K$5:K$38) -> 1216.9934 | I2: =SUMIF(Escondida!$B$5:$B$38,Locations!$B2,Escondida!L$5:L$38) -> 884.98836 | J2: =SUMIF(Escondida!$B$5:$B$38,Locations!$B2,Escondida!M$5:M$38) -> 1209.2171 | K2: =SUMIF(Escondida!$B$5:$B$38,Locations!$B2,Escondida!N$5:N$38) -> 1146.9052 | ... O2: =SUMIF(Escondida!$B$5:$B$38,Locations!$B2,Escondida!R$5:R$38) -> 926.96485 | P2: =SUM(D2:O2) -> 12001.718
B3: BOMBEO3_______004 | C3: Bombeo | D3: =SUMIF(Escondida!$B$5:$B$38,Locations!$B3,Escondida!G$5:G$38) -> 1163.503 | E3: =SUMIF(Escondida!$B$5:$B$38,Locations!$B3,Escondida!H$5:H$38) -> 1023.3025 | F3: =SUMIF(Escondida!$B$5:$B$38,Locations!$B3,Escondida!I$5:I$38) -> 1074.7114 | G3: =SUMIF(Escondida!$B$5:$B$38,Locations!$B3,Escondida!J$5:J$38) -> 1220.6069 | H3: =SUMIF(Escondida!$B$5:$B$38,Locations!$B3,Escondida!K$5:K$38) -> 1175.8786 | I3: =SUMIF(Escondida!$B$5:$B$38,Locations!$B3,Escondida!L$5:L$38) -> 848.164 | J3: =SUMIF(Escondida!$B$5:$B$38,Locations!$B3,Escondida!M$5:M$38) -> 1193.1516 | K3: =SUMIF(Escondida!$B$5:$B$38,Locations!$B3,Escondida!N$5:N$38) -> 1356.4937 | ... O3: =SUMIF(Escondida!$B$5:$B$38,Locations!$B3,Escondida!R$5:R$38) -> 972.15047 | P3: =SUM(D3:O3) -> 13580.24
B4: BOMBEO4_______004 | C4: Bombeo | D4: =SUMIF(Escondida!$B$5:$B$38,Locations!$B4,Escondida!G$5:G$38) -> 1212.9185 | E4: =SUMIF(Escondida!$B$5:$B$38,Locations!$B4,Escondida!H$5:H$38) -> 989.78342 | F4: =SUMIF(Escondida!$B$5:$B$38,Locations!$B4,Escondida!I$5:I$38) -> 1089.6744 | G4: =SUMIF(Escondida!$B$5:$B$38,Locations!$B4,Escondida!J$5:J$38) -> 1267.701 | H4: =SUMIF(Escondida!$B$5:$B$38,Locations!$B4,Escondida!K$5:K$38) -> 1225.1075 | I4: =SUMIF(Escondida!$B$5:$B$38,Locations!$B4,Escondida!L$5:L$38) -> 857.19414 | J4: =SUMIF(Escondida!$B$5:$B$38,Locations!$B4,Escondida!M$5:M$38) -> 1179.9348 | K4: =SUMIF(Escondida!$B$5:$B$38,Locations!$B4,Escondida!N$5:N$38) -> 1199.279 | ... O4: =SUMIF(Escondida!$B$5:$B$38,Locations!$B4,Escondida!R$5:R$38) -> 886.32664 | P4: =SUM(D4:O4) -> 13151.244
B5: CHIMBORAZO____220 | C5: Minera | D5: =SUMIF(Escondida!$B$5:$B$38,Locations!$B5,Escondida!G$5:G$38) -> 27269.015 | E5: =SUMIF(Escondida!$B$5:$B$38,Locations!$B5,Escondida!H$5:H$38) -> 26478.034 | F5: =SUMIF(Escondida!$B$5:$B$38,Locations!$B5,Escondida!I$5:I$38) -> 27638.182 | G5: =SUMIF(Escondida!$B$5:$B$38,Locations!$B5,Escondida!J$5:J$38) -> 28803.39 | H5: =SUMIF(Escondida!$B$5:$B$38,Locations!$B5,Escondida!K$5:K$38) -> 30512.064 | I5: =SUMIF(Escondida!$B$5:$B$38,Locations!$B5,Escondida!L$5:L$38) -> 27099.968 | J5: =SUMIF(Escondida!$B$5:$B$38,Locations!$B5,Escondida!M$5:M$38) -> 25061.936 | K5: =SUMIF(Escondida!$B$5:$B$38,Locations!$B5,Escondida!N$5:N$38) -> 26369.195 | ... O5: =SUMIF(Escondida!$B$5:$B$38,Locations!$B5,Escondida!R$5:R$38) -> 31391.053 | P5: =SUM(D5:O5) -> 331092.7
B6: COLOSO________220 | C6: Desalinacion | D6: =SUMIF(Escondida!$B$5:$B$38,Locations!$B6,Escondida!G$5:G$38) -> 58143.145 | E6: =SUMIF(Escondida!$B$5:$B$38,Locations!$B6,Escondida!H$5:H$38) -> 56262.047 | F6: =SUMIF(Escondida!$B$5:$B$38,Locations!$B6,Escondida!I$5:I$38) -> 60006.624 | G6: =SUMIF(Escondida!$B$5:$B$38,Locations!$B6,Escondida!J$5:J$38) -> 62679.326 | H6: =SUMIF(Escondida!$B$5:$B$38,Locations!$B6,Escondida!K$5:K$38) -> 65148.336 | I6: =SUMIF(Escondida!$B$5:$B$38,Locations!$B6,Escondida!L$5:L$38) -> 57371.327 | J6: =SUMIF(Escondida!$B$5:$B$38,Locations!$B6,Escondida!M$5:M$38) -> 53985.378 | K6: =SUMIF(Escondida!$B$5:$B$38,Locations!$B6,Escondida!N$5:N$38) -> 57250.516 | ... O6: =SUMIF(Escondida!$B$5:$B$38,Locations!$B6,Escondida!R$5:R$38) -> 65415.006 | P6: =SUM(D6:O6) -> 708524.68
B7: DOMEYKO_______220 | C7: Minera | D7: =SUMIF(Escondida!$B$5:$B$38,Locations!$B7,Escondida!G$5:G$38) -> 97903.84 | E7: =SUMIF(Escondida!$B$5:$B$38,Locations!$B7,Escondida!H$5:H$38) -> 89881.523 | F7: =SUMIF(Escondida!$B$5:$B$38,Locations!$B7,Escondida!I$5:I$38) -> 108541.82 | G7: =SUMIF(Escondida!$B$5:$B$38,Locations!$B7,Escondida!J$5:J$38) -> 103268.1 | H7: =SUMIF(Escondida!$B$5:$B$38,Locations!$B7,Escondida!K$5:K$38) -> 114235.92 | I7: =SUMIF(Escondida!$B$5:$B$38,Locations!$B7,Escondida!L$5:L$38) -> 95525.039 | J7: =SUMIF(Escondida!$B$5:$B$38,Locations!$B7,Escondida!M$5:M$38) -> 112482.3 | K7: =SUMIF(Escondida!$B$5:$B$38,Locations!$B7,Escondida!N$5:N$38) -> 112069.56 | ... O7: =SUMIF(Escondida!$B$5:$B$38,Locations!$B7,Escondida!R$5:R$38) -> 102976.76 | P7: =SUM(D7:O7) -> 1241521.7
B8: ESCONDIDA_____220 | C8: Minera | D8: =SUMIF(Escondida!$B$5:$B$38,Locations!$B8,Escondida!G$5:G$38) -> 70180.705 | E8: =SUMIF(Escondida!$B$5:$B$38,Locations!$B8,Escondida!H$5:H$38) -> 69259.806 | F8: =SUMIF(Escondida!$B$5:$B$38,Locations!$B8,Escondida!I$5:I$38) -> 79886.517 | G8: =SUMIF(Escondida!$B$5:$B$38,Locations!$B8,Escondida!J$5:J$38) -> 85001.331 | H8: =SUMIF(Escondida!$B$5:$B$38,Locations!$B8,Escondida!K$5:K$38) -> 77263.231 | I8: =SUMIF(Escondida!$B$5:$B$38,Locations!$B8,Escondida!L$5:L$38) -> 74234.266 | J8: =SUMIF(Escondida!$B$5:$B$38,Locations!$B8,Escondida!M$5:M$38) -> 67198.559 | K8: =SUMIF(Escondida!$B$5:$B$38,Locations!$B8,Escondida!N$5:N$38) -> 74674.386 | ... O8: =SUMIF(Escondida!$B$5:$B$38,Locations!$B8,Escondida!R$5:R$38) -> 81323.3 | P8: =SUM(D8:O8) -> 889249.72
B9: FARELLON______220 | C9: Bombeo | D9: =SUMIF(Escondida!$B$5:$B$38,Locations!$B9,Escondida!G$5:G$38) -> 28037.162 | E9: =SUMIF(Escondida!$B$5:$B$38,Locations!$B9,Escondida!H$5:H$38) -> 27312.761 | F9: =SUMIF(Escondida!$B$5:$B$38,Locations!$B9,Escondida!I$5:I$38) -> 28223.522 | G9: =SUMIF(Escondida!$B$5:$B$38,Locations!$B9,Escondida!J$5:J$38) -> 29696.124 | H9: =SUMIF(Escondida!$B$5:$B$38,Locations!$B9,Escondida!K$5:K$38) -> 31584.449 | I9: =SUMIF(Escondida!$B$5:$B$38,Locations!$B9,Escondida!L$5:L$38) -> 27836.085 | J9: =SUMIF(Escondida!$B$5:$B$38,Locations!$B9,Escondida!M$5:M$38) -> 25511.419 | K9: =SUMIF(Escondida!$B$5:$B$38,Locations!$B9,Escondida!N$5:N$38) -> 26910.52 | ... O9: =SUMIF(Escondida!$B$5:$B$38,Locations!$B9,Escondida!R$5:R$38) -> 31870.647 | P9: =SUM(D9:O9) -> 338849.05
B10: OGP1__________220 | C10: Minera | D10: =SUMIF(Escondida!$B$5:$B$38,Locations!$B10,Escondida!G$5:G$38) -> 86938.798 | E10: =SUMIF(Escondida!$B$5:$B$38,Locations!$B10,Escondida!H$5:H$38) -> 87929.412 | F10: =SUMIF(Escondida!$B$5:$B$38,Locations!$B10,Escondida!I$5:I$38) -> 83848.764 | G10: =SUMIF(Escondida!$B$5:$B$38,Locations!$B10,Escondida!J$5:J$38) -> 99110.904 | H10: =SUMIF(Escondida!$B$5:$B$38,Locations!$B10,Escondida!K$5:K$38) -> 104199.71 | I10: =SUMIF(Escondida!$B$5:$B$38,Locations!$B10,Escondida!L$5:L$38) -> 98548.005 | J10: =SUMIF(Escondida!$B$5:$B$38,Locations!$B10,Escondida!M$5:M$38) -> 102354.04 | K10: =SUMIF(Escondida!$B$5:$B$38,Locations!$B10,Escondida!N$5:N$38) -> 109877.05 | ... O10: =SUMIF(Escondida!$B$5:$B$38,Locations!$B10,Escondida!R$5:R$38) -> 97365.921 | P10: =SUM(D10:O10) -> 1162232.8
B11: PURI__________220 | C11: Bombeo | D11: =SUMIF(Escondida!$B$5:$B$38,Locations!$B11,Escondida!G$5:G$38) -> 28325.414 | E11: =SUMIF(Escondida!$B$5:$B$38,Locations!$B11,Escondida!H$5:H$38) -> 27524.102 | F11: =SUMIF(Escondida!$B$5:$B$38,Locations!$B11,Escondida!I$5:I$38) -> 28685.439 | G11: =SUMIF(Escondida!$B$5:$B$38,Locations!$B11,Escondida!J$5:J$38) -> 29967.123 | H11: =SUMIF(Escondida!$B$5:$B$38,Locations!$B11,Escondida!K$5:K$38) -> 31922.242 | I11: =SUMIF(Escondida!$B$5:$B$38,Locations!$B11,Escondida!L$5:L$38) -> 27966.668 | J11: =SUMIF(Escondida!$B$5:$B$38,Locations!$B11,Escondida!M$5:M$38) -> 26095.733 | K11: =SUMIF(Escondida!$B$5:$B$38,Locations!$B11,Escondida!N$5:N$38) -> 27244.813 | ... O11: =SUMIF(Escondida!$B$5:$B$38,Locations!$B11,Escondida!R$5:R$38) -> 32542.983 | P11: =SUM(D11:O11) -> 343196.92
B12: SULFUROS______220 | C12: Minera | D12: =SUMIF(Escondida!$B$5:$B$38,Locations!$B12,Escondida!G$5:G$38) -> 48095.972 | E12: =SUMIF(Escondida!$B$5:$B$38,Locations!$B12,Escondida!H$5:H$38) -> 43651.651 | F12: =SUMIF(Escondida!$B$5:$B$38,Locations!$B12,Escondida!I$5:I$38) -> 50760.216 | G12: =SUMIF(Escondida!$B$5:$B$38,Locations!$B12,Escondida!J$5:J$38) -> 49048.336 | H12: =SUMIF(Escondida!$B$5:$B$38,Locations!$B12,Escondida!K$5:K$38) -> 50718.681 | I12: =SUMIF(Escondida!$B$5:$B$38,Locations!$B12,Escondida!L$5:L$38) -> 50354.384 | J12: =SUMIF(Escondida!$B$5:$B$38,Locations!$B12,Escondida!M$5:M$38) -> 41932.66 | K12: =SUMIF(Escondida!$B$5:$B$38,Locations!$B12,Escondida!N$5:N$38) -> 43993.938 | ... O12: =SUMIF(Escondida!$B$5:$B$38,Locations!$B12,Escondida!R$5:R$38) -> 51298.537 | P12: =SUM(D12:O12) -> 576054.26
B13: SUR___________110 | C13: no consumo | D13: =SUMIF(Escondida!$B$5:$B$38,Locations!$B13,Escondida!G$5:G$38) -> 0 | E13: =SUMIF(Escondida!$B$5:$B$38,Locations!$B13,Escondida!H$5:H$38) -> 0 | F13: =SUMIF(Escondida!$B$5:$B$38,Locations!$B13,Escondida!I$5:I$38) -> 0 | G13: =SUMIF(Escondida!$B$5:$B$38,Locations!$B13,Escondida!J$5:J$38) -> 0 | H13: =SUMIF(Escondida!$B$5:$B$38,Locations!$B13,Escondida!K$5:K$38) -> 0 | I13: =SUMIF(Escondida!$B$5:$B$38,Locations!$B13,Escondida!L$5:L$38) -> 0 | J13: =SUMIF(Escondida!$B$5:$B$38,Locations!$B13,Escondida!M$5:M$38) -> 0 | K13: =SUMIF(Escondida!$B$5:$B$38,Locations!$B13,Escondida!N$5:N$38) -> 0 | ... O13: =SUMIF(Escondida!$B$5:$B$38,Locations!$B13,Escondida!R$5:R$38) -> 0 | P13: =SUM(D13:O13) -> 0
C15: Tipo | D15: ene-25 | E15: feb-25 | F15: mar-25 | G15: abr-25 | H15: may-25 | I15: jun-25 | J15: jul-25 | K15: ago-25 | L15: sept-25 | M15: oct-25 | N15: nov-25 | O15: dic-25 | P15: TOTAL
C16: Bombeo | D16: =SUMIF($C$2:$C$13,$C16,D$2:D$13) -> 59699.032 | E16: =SUMIF($C$2:$C$13,$C16,E$2:E$13) -> 57637.283 | F16: =SUMIF($C$2:$C$13,$C16,F$2:F$13) -> 59991.375 | G16: =SUMIF($C$2:$C$13,$C16,G$2:G$13) -> 63240.624 | H16: =SUMIF($C$2:$C$13,$C16,H$2:H$13) -> 67124.669 | I16: =SUMIF($C$2:$C$13,$C16,I$2:I$13) -> 58393.099 | J16: =SUMIF($C$2:$C$13,$C16,J$2:J$13) -> 55189.456 | K16: =SUMIF($C$2:$C$13,$C16,K$2:K$13) -> 57858.01 | ... O16: =SUMIF($C$2:$C$13,$C16,O$2:O$13) -> 67199.071 | P16: =SUM(D16:O16) -> 720779.17
C17: Minera | D17: =SUMIF($C$2:$C$13,$C17,D$2:D$13) -> 330388.33 | E17: =SUMIF($C$2:$C$13,$C17,E$2:E$13) -> 317200.42 | F17: =SUMIF($C$2:$C$13,$C17,F$2:F$13) -> 350675.5 | G17: =SUMIF($C$2:$C$13,$C17,G$2:G$13) -> 365232.06 | H17: =SUMIF($C$2:$C$13,$C17,H$2:H$13) -> 376929.61 | I17: =SUMIF($C$2:$C$13,$C17,I$2:I$13) -> 345761.66 | J17: =SUMIF($C$2:$C$13,$C17,J$2:J$13) -> 349029.5 | K17: =SUMIF($C$2:$C$13,$C17,K$2:K$13) -> 366984.13 | ... O17: =SUMIF($C$2:$C$13,$C17,O$2:O$13) -> 364355.57 | P17: =SUM(D17:O17) -> 4200151.2
C18: Desalinacion | D18: =SUMIF($C$2:$C$13,$C18,D$2:D$13) -> 58143.145 | E18: =SUMIF($C$2:$C$13,$C18,E$2:E$13) -> 56262.047 | F18: =SUMIF($C$2:$C$13,$C18,F$2:F$13) -> 60006.624 | G18: =SUMIF($C$2:$C$13,$C18,G$2:G$13) -> 62679.326 | H18: =SUMIF($C$2:$C$13,$C18,H$2:H$13) -> 65148.336 | I18: =SUMIF($C$2:$C$13,$C18,I$2:I$13) -> 57371.327 | J18: =SUMIF($C$2:$C$13,$C18,J$2:J$13) -> 53985.378 | K18: =SUMIF($C$2:$C$13,$C18,K$2:K$13) -> 57250.516 | ... O18: =SUMIF($C$2:$C$13,$C18,O$2:O$13) -> 65415.006 | P18: =SUM(D18:O18) -> 708524.68

Sheet Sources
A2: subestationes | B2: https://mapache.ai/energia/subestaciones
A3: consumo | B3: https://www.coordinador.cl/clienteslibres/
